Workbook

Sheet Accueil
B2: Plan Financier et Stratégique d'AéroTech Maroc
B3: Analyse financière CGNC · Reporting · Tableau de bord — Exercice 2023
B5: IDENTIFICATION
B6: Nom de l'entreprise | C6: AéroTech Maroc
B7: Secteur | C7: Aéronautique
B8: Date | C8: 31 décembre 2023
B9: Département | C9: Finance
B10: Responsable | C10: Mme Amal Bennani
B12: SOMMAIRE
B13: → Balance | C13: Balance comptable CGNC (classes 1 à 7) sur 12 mois — seul onglet de saisie
B14: → CPC | C14: Compte de produits et charges, modèle normal CGNC, calculé automatiquement
B15: → ESG | C15: État des soldes de gestion : TFR (marge, VA, EBE…) et CAF
B16: → Reporting | C16: Élasticité CA/REX codée par couleur et KPI clés, avec sélecteur de mois
B17: → DASHBOARD | C17: Cartes et graphiques de tendance interactifs (grenat et doré)
B18: → Lecture | C18: Explications vulgarisées de chaque indicateur
B20: MODE D'EMPLOI
B21: 1. Saisissez ou collez vos montants uniquement dans l'onglet « Balance » (chiffres en bleu).
B22: 2. Classes 1 à 5 : solde de fin de mois. Classes 6 et 7 : mouvement du mois (pas le cumul).
B23: 3. Vérifiez que la ligne « Contrôle d'équilibre » de la Balance affiche 0 pour chaque mois.
B24: 4. Le CPC, l'ESG, le Reporting et le Dashboard se recalculent seuls : aucune formule à toucher.
B25: 5. Dans le Reporting (C4) et le Dashboard (D4), choisissez un mois dans la liste pour l'analyser.
B26: 6. Pour comprendre un indicateur ou une couleur, consultez l'onglet « Lecture ».
B27: 7. Pour ajouter un compte : insérez une ligne à l'intérieur du bloc de la Balance (avant la dernière ligne de compte).
B29: CONTRÔLES DE COHÉRENCE (automatiques)
B30: Balance équilibrée (12 mois) | C30: =IF(SUMPRODUCT(ABS(Balance!E77:Q77))<1,"✔ OK","✖ Écart à vérifier") -> ✔ OK
B31: CPC : résultat net (2 méthodes) | C31: =IF(SUMPRODUCT(ABS(CPC!D60:P60))<1,"✔ OK","✖ Écart à vérifier") -> ✔ OK
B32: ESG = CPC (résultat net) | C32: =IF(SUMPRODUCT(ABS(ESG!D43:P43))<1,"✔ OK","✖ Écart à vérifier") -> ✔ OK
B34: LÉGENDE
B35: 1 234 567 | C35: Chiffre en bleu : donnée saisie (modifiable)
B36: 1 234 567 | C36: Chiffre en noir : formule (ne pas modifier)
B37: Décembre | C37: Case dorée : sélecteur de mois (liste déroulante)
B39: Note : Toutes les données chiffrées générées dans ce fichier sont fictives.

Sheet Balance
A1: BALANCE COMPTABLE CGNC — AéroTech Maroc — Exercice 2023 | R1: ⌂ Accueil
A2: Montants en MAD · Classes 1 à 5 : soldes de fin de mois · Classes 6 et 7 : mouvements du mois · Données fictives
A3: Légende : | B3: Chiffres en bleu = données saisies (modifiables). Tous les autres onglets se recalculent automatiquement.
A5: Compte | B5: Intitulé | C5: Classe | D5: Sens | E5: Ouverture 01/01 | F5: Janvier | G5: Février | H5: Mars | I5: Avril | J5: Mai | K5: Juin | L5: Juillet | M5: Août | N5: Septembre | O5: Octobre | P5: Novembre | Q5: Décembre | R5: Total / Clôture
B6: CLASSE 1 — COMPTES DE FINANCEMENT PERMANENT
A7: 1111 | B7: Capital social | C7: =VALUE(LEFT(A7,1)) -> 1 | D7: C | E7: 20000000 | F7: 20000000 | G7: 20000000 | H7: 20000000 | I7: 20000000 | J7: 20000000 | K7: 20000000 | L7: 20000000 | M7: 20000000 | N7: 20000000 | O7: 20000000 | P7: 20000000 | Q7: 20000000 | R7: =Q7 -> 20000000
A8: 1140 | B8: Réserve légale | C8: =VALUE(LEFT(A8,1)) -> 1 | D8: C | E8: 2000000 | F8: 2000000 | G8: 2000000 | H8: 2000000 | I8: 2000000 | J8: 2000000 | K8: 2000000 | L8: 2000000 | M8: 2000000 | N8: 2000000 | O8: 2000000 | P8: 2000000 | Q8: 2000000 | R8: =Q8 -> 2000000
A9: 1161 | B9: Report à nouveau (solde créditeur) | C9: =VALUE(LEFT(A9,1)) -> 1 | D9: C | E9: 10000000 | F9: 10000000 | G9: 10000000 | H9: 10000000 | I9: 10000000 | J9: 10000000 | K9: 10000000 | L9: 10000000 | M9: 10000000 | N9: 10000000 | O9: 10000000 | P9: 10000000 | Q9: 10000000 | R9: =Q9 -> 10000000
A10: 1481 | B10: Emprunts auprès des établissements de crédit | C10: =VALUE(LEFT(A10,1)) -> 1 | D10: C | E10: 24000000 | F10: 23700000 | G10: 23400000 | H10: 23100000 | I10: 22800000 | J10: 22500000 | K10: 22200000 | L10: 21900000 | M10: 21600000 | N10: 21300000 | O10: 21000000 | P10: 20700000 | Q10: 20400000 | R10: =Q10 -> 20400000
B11: CLASSE 2 — COMPTES D'ACTIF IMMOBILISÉ
A12: 2321 | B12: Bâtiments | C12: =VALUE(LEFT(A12,1)) -> 2 | D12: D | E12: 15000000 | F12: 15000000 | G12: 15000000 | H12: 15000000 | I12: 15000000 | J12: 15000000 | K12: 15000000 | L12: 15000000 | M12: 15000000 | N12: 15000000 | O12: 15000000 | P12: 15000000 | Q12: 15000000 | R12: =Q12 -> 15000000
A13: 2332 | B13: Matériel et outillage | C13: =VALUE(LEFT(A13,1)) -> 2 | D13: D | E13: 32000000 | F13: 32000000 | G13: 32000000 | H13: 32120000 | I13: 33920000 | J13: 33920000 | K13: 33920000 | L13: 33920000 | M13: 33920000 | N13: 34015000 | O13: 34015000 | P13: 34015000 | Q13: 34015000 | R13: =Q13 -> 34015000
A14: 2340 | B14: Matériel de transport | C14: =VALUE(LEFT(A14,1)) -> 2 | D14: D | E14: 1600000 | F14: 1600000 | G14: 1600000 | H14: 1600000 | I14: 1600000 | J14: 1600000 | K14: 1600000 | L14: 1600000 | M14: 1600000 | N14: 1600000 | O14: 1200000 | P14: 1200000 | Q14: 1200000 | R14: =Q14 -> 1200000
A15: 2355 | B15: Matériel informatique | C15: =VALUE(LEFT(A15,1)) -> 2 | D15: D | E15: 1400000 | F15: 1400000 | G15: 1400000 | H15: 1400000 | I15: 1400000 | J15: 1400000 | K15: 1400000 | L15: 1400000 | M15: 1400000 | N15: 1400000 | O15: 1400000 | P15: 1400000 | Q15: 1400000 | R15: =Q15 -> 1400000
A16: 2832 | B16: Amortissements des constructions | C16: =VALUE(LEFT(A16,1)) -> 2 | D16: C | E16: 4500000 | F16: 4562500 | G16: 4625000 | H16: 4687500 | I16: 4750000 | J16: 4812500 | K16: 4875000 | L16: 4937500 | M16: 5000000 | N16: 5062500 | O16: 5125000 | P16: 5187500 | Q16: 5250000 | R16: =Q16 -> 5250000
A17: 2833 | B17: Amortissements des installations techniques, matériel et outillage | C17: =VALUE(LEFT(A17,1)) -> 2 | D17: C | E17: 13000000 | F17: 13240000 | G17: 13480000 | H17: 13720000 | I17: 13960000 | J17: 14215000 | K17: 14470000 | L17: 14725000 | M17: 14980000 | N17: 15235000 | O17: 15490000 | P17: 15745000 | Q17: 16000000 | R17: =Q17 -> 16000000
A18: 2834 | B18: Amortissements du matériel de transport | C18: =VALUE(LEFT(A18,1)) -> 2 | D18: C | E18: 800000 | F18: 830000 | G18: 860000 | H18: 890000 | I18: 920000 | J18: 950000 | K18: 980000 | L18: 1010000 | M18: 1040000 | N18: 1070000 | O18: 810000 | P18: 832000 | Q18: 854000 | R18: =Q18 -> 854000
A19: 2835 | B19: Amortissements du mobilier, matériel de bureau et aménagements divers | C19: =VALUE(LEFT(A19,1)) -> 2 | D19: C | E19: 600000 | F19: 650000 | G19: 700000 | H19: 750000 | I19: 800000 | J19: 850000 | K19: 900000 | L19: 950000 | M19: 1000000 | N19: 1050000 | O19: 1100000 | P19: 1150000 | Q19: 1200000 | R19: =Q19 -> 1200000
B20: CLASSE 3 — COMPTES D'ACTIF CIRCULANT
A21: 3121 | B21: Matières premières (titane, aluminium, composites) | C21: =VALUE(LEFT(A21,1)) -> 3 | D21: D | E21: 4500000 | F21: 4491000 | G21: 4366000 | H21: 4559000 | I21: 4515000 | J21: 4677000 | K21: 4667000 | L21: 4643000 | M21: 4598000 | N21: 4534000 | O21: 4300000 | P21: 4489000 | Q21: 4685000 | R21: =Q21 -> 4685000
A22: 3131 | B22: Biens en cours | C22: =VALUE(LEFT(A22,1)) -> 3 | D22: D | E22: 9000000 | F22: 8891000 | G22: 9332000 | H22: 8931000 | I22: 8879000 | J22: 9105000 | K22: 9284000 | L22: 9366000 | M22: 9445000 | N22: 9156000 | O22: 9625000 | P22: 9622000 | Q22: 9450000 | R22: =Q22 -> 9450000
A23: 3151 | B23: Produits finis | C23: =VALUE(LEFT(A23,1)) -> 3 | D23: D | E23: 3000000 | F23: 3010000 | G23: 2916000 | H23: 3138000 | I23: 3036000 | J23: 3116000 | K23: 3072000 | L23: 3122000 | M23: 3106000 | N23: 3165000 | O23: 3110000 | P23: 2992000 | Q23: 3228000 | R23: =Q23 -> 3228000
A24: 3421 | B24: Clients | C24: =VALUE(LEFT(A24,1)) -> 3 | D24: D | E24: 14233000 | F24: 13008000 | G24: 14800000 | H24: 15364000 | I24: 15216000 | J24: 14074000 | K24: 16587000 | L24: 15072000 | M24: 11500000 | N24: 15610000 | O24: 15194000 | P24: 16682000 | Q24: 15516000 | R24: =Q24 -> 15516000
A25: 3455 | B25: État — TVA récupérable | C25: =VALUE(LEFT(A25,1)) -> 3 | D25: D | E25: 300000 | F25: 252000 | G25: 274000 | H25: 307000 | I25: 272000 | J25: 323000 | K25: 339000 | L25: 293000 | M25: 236000 | N25: 279000 | O25: 308000 | P25: 317000 | Q25: 337000 | R25: =Q25 -> 337000
A26: 3942 | B26: Provisions pour dépréciation des clients et comptes rattachés | C26: =VALUE(LEFT(A26,1)) -> 3 | D26: C | E26: 180000 | F26: 180000 | G26: 180000 | H26: 180000 | I26: 180000 | J26: 180000 | K26: 240000 | L26: 240000 | M26: 240000 | N26: 240000 | O26: 240000 | P26: 240000 | Q26: 285000 | R26: =Q26 -> 285000
B27: CLASSE 4 — COMPTES DE PASSIF CIRCULANT
A28: 4411 | B28: Fournisseurs | C28: =VALUE(LEFT(A28,1)) -> 4 | D28: C | E28: 9680000 | F28: 7571000 | G28: 8119000 | H28: 9137000 | I28: 8719000 | J28: 9313000 | K28: 9788000 | L28: 9884000 | M28: 7297000 | N28: 9104000 | O28: 9824000 | P28: 9664000 | Q28: 10985000 | R28: =Q28 -> 10985000
A29: 4432 | B29: Rémunérations dues au personnel | C29: =VALUE(LEFT(A29,1)) -> 4 | D29: C | E29: 180000 | F29: 182000 | G29: 183000 | H29: 184000 | I29: 185000 | J29: 185000 | K29: 186000 | L29: 187000 | M29: 188000 | N29: 188000 | O29: 189000 | P29: 190000 | Q29: 205000 | R29: =Q29 -> 205000
A30: 4441 | B30: Caisse nationale de sécurité sociale | C30: =VALUE(LEFT(A30,1)) -> 4 | D30: C | E30: 320000 | F30: 319000 | G30: 320000 | H30: 322000 | I30: 323000 | J30: 324000 | K30: 326000 | L30: 327000 | M30: 328000 | N30: 329000 | O30: 331000 | P30: 332000 | Q30: 358000 | R30: =Q30 -> 358000
A31: 4453 | B31: État — impôts sur les résultats | C31: =VALUE(LEFT(A31,1)) -> 4 | D31: C | E31: 0 | F31: 93700 | G31: 278300 | H31: 0 | I31: 157100 | J31: 365800 | K31: 0 | L31: 205100 | M31: 258400 | N31: 0 | O31: 266800 | P31: 479300 | Q31: 0 | R31: =Q31 -> 0
A32: 4455 | B32: État — TVA facturée | C32: =VALUE(LEFT(A32,1)) -> 4 | D32: C | E32: 30000 | F32: 215000 | G32: 229000 | H32: 251000 | I32: 238000 | J32: 250000 | K32: 260000 | L32: 246000 | M32: 199000 | N32: 245000 | O32: 263000 | P32: 262000 | Q32: 274000 | R32: =Q32 -> 274000
B33: CLASSE 5 — COMPTES DE TRÉSORERIE
A34: 5141 | B34: Banques (soldes débiteurs) | C34: =VALUE(LEFT(A34,1)) -> 5 | D34: D | E34: 4227000 | F34: 4236000 | G34: 3769300 | H34: 4680000 | I34: 3699900 | J34: 6071100 | K34: 4233600 | L34: 6893400 | M34: 8236500 | N34: 6656300 | O34: 9146000 | P34: 8574000 | Q34: 11360200 | R34: =Q34 -> 11360200
A35: 5161 | B35: Caisse | C35: =VALUE(LEFT(A35,1)) -> 5 | D35: D | E35: 30000 | F35: 30000 | G35: 30000 | H35: 30000 | I35: 30000 | J35: 30000 | K35: 30000 | L35: 30000 | M35: 30000 | N35: 30000 | O35: 30000 | P35: 30000 | Q35: 30000 | R35: =Q35 -> 30000
B36: CLASSE 6 — COMPTES DE CHARGES (mouvements du mois)
A37: 6111 | B37: Achats de marchandises | C37: =VALUE(LEFT(A37,1)) -> 6 | D37: D | F37: 94000 | G37: 100000 | H37: 110000 | I37: 104000 | J37: 109000 | K37: 113000 | L37: 107000 | M37: 87000 | N37: 107000 | O37: 115000 | P37: 114000 | Q37: 119000 | R37: =SUM(F37:Q37) -> 1279000
A38: 6121 | B38: Achats de matières premières | C38: =VALUE(LEFT(A38,1)) -> 6 | D38: D | F38: 2360000 | G38: 2563000 | H38: 2976000 | I38: 2557000 | J38: 3075000 | K38: 2949000 | L38: 2775000 | M38: 2202000 | N38: 2622000 | O38: 2864000 | P38: 3074000 | Q38: 3283000 | R38: =SUM(F38:Q38) -> 33300000
A39: 6122 | B39: Achats de matières et fournitures consommables | C39: =VALUE(LEFT(A39,1)) -> 6 | D39: D | F39: 187000 | G39: 212000 | H39: 220000 | I39: 205000 | J39: 230000 | K39: 234000 | L39: 221000 | M39: 177000 | N39: 212000 | O39: 245000 | P39: 228000 | Q39: 244000 | R39: =SUM(F39:Q39) -> 2615000
A40: 6124 | B40: Variation des stocks de matières et fournitures (±) | C40: =VALUE(LEFT(A40,1)) -> 6 | D40: D | F40: 9000 | G40: 125000 | H40: -193000 | I40: 44000 | J40: -162000 | K40: 10000 | L40: 24000 | M40: 45000 | N40: 64000 | O40: 234000 | P40: -189000 | Q40: -196000 | R40: =SUM(F40:Q40) -> -185000
A41: 6125 | B41: Achats non stockés de matières et fournitures (énergie, eau) | C41: =VALUE(LEFT(A41,1)) -> 6 | D41: D | F41: 218000 | G41: 248000 | H41: 256000 | I41: 240000 | J41: 268000 | K41: 273000 | L41: 258000 | M41: 207000 | N41: 247000 | O41: 285000 | P41: 266000 | Q41: 284000 | R41: =SUM(F41:Q41) -> 3050000
A42: 6126 | B42: Achats de travaux, études et prestations de services (sous-traitance) | C42: =VALUE(LEFT(A42,1)) -> 6 | D42: D | F42: 312000 | G42: 354000 | H42: 366000 | I42: 342000 | J42: 383000 | K42: 389000 | L42: 368000 | M42: 296000 | N42: 353000 | O42: 408000 | P42: 380000 | Q42: 406000 | R42: =SUM(F42:Q42) -> 4357000
A43: 6131 | B43: Locations et charges locatives | C43: =VALUE(LEFT(A43,1)) -> 6 | D43: D | F43: 85000 | G43: 85000 | H43: 85000 | I43: 85000 | J43: 85000 | K43: 85000 | L43: 85000 | M43: 85000 | N43: 85000 | O43: 85000 | P43: 85000 | Q43: 85000 | R43: =SUM(F43:Q43) -> 1020000
A44: 6133 | B44: Entretien et réparations | C44: =VALUE(LEFT(A44,1)) -> 6 | D44: D | F44: 94000 | G44: 106000 | H44: 110000 | I44: 103000 | J44: 115000 | K44: 537000 | L44: 110000 | M44: 89000 | N44: 106000 | O44: 122000 | P44: 114000 | Q44: 122000 | R44: =SUM(F44:Q44) -> 1728000
A45: 6134 | B45: Primes d'assurances | C45: =VALUE(LEFT(A45,1)) -> 6 | D45: D | F45: 40000 | G45: 40000 | H45: 40000 | I45: 40000 | J45: 40000 | K45: 40000 | L45: 40000 | M45: 40000 | N45: 40000 | O45: 40000 | P45: 40000 | Q45: 40000 | R45: =SUM(F45:Q45) -> 480000
A46: 6136 | B46: Rémunérations d'intermédiaires et honoraires | C46: =VALUE(LEFT(A46,1)) -> 6 | D46: D | F46: 35000 | G46: 35000 | H46: 35000 | I46: 35000 | J46: 125000 | K46: 35000 | L46: 35000 | M46: 35000 | N46: 35000 | O46: 35000 | P46: 35000 | Q46: 35000 | R46: =SUM(F46:Q46) -> 510000
A47: 6142 | B47: Transports | C47: =VALUE(LEFT(A47,1)) -> 6 | D47: D | F47: 116000 | G47: 124000 | H47: 136000 | I47: 129000 | J47: 135000 | K47: 140000 | L47: 133000 | M47: 107000 | N47: 132000 | O47: 142000 | P47: 142000 | Q47: 148000 | R47: =SUM(F47:Q47) -> 1584000
A48: 6143 | B48: Déplacements, missions et réceptions | C48: =VALUE(LEFT(A48,1)) -> 6 | D48: D | F48: 25000 | G48: 25000 | H48: 25000 | I48: 25000 | J48: 25000 | K48: 25000 | L48: 25000 | M48: 25000 | N48: 25000 | O48: 25000 | P48: 25000 | Q48: 25000 | R48: =SUM(F48:Q48) -> 300000
... A62: 6701 | B62: Impôts sur les bénéfices | C62: =VALUE(LEFT(A62,1)) -> 6 | D62: D | F62: 93700 | G62: 184600 | H62: 198600 | I62: 157100 | J62: 208700 | K62: 134200 | L62: 205100 | M62: 53300 | N62: 170200 | O62: 266800 | P62: 212500 | Q62: 217800 | R62: =SUM(F62:Q62) -> 2102600
B63: CLASSE 7 — COMPTES DE PRODUITS (mouvements du mois)
A64: 7111 | B64: Ventes de marchandises au Maroc | C64: =VALUE(LEFT(A64,1)) -> 7 | D64: C | F64: 127000 | G64: 135000 | H64: 148000 | I64: 140000 | J64: 147000 | K64: 153000 | L64: 145000 | M64: 117000 | N64: 144000 | O64: 155000 | P64: 154000 | Q64: 161000 | R64: =SUM(F64:Q64) -> 1726000
A65: 7121 | B65: Ventes de biens produits au Maroc | C65: =VALUE(LEFT(A65,1)) -> 7 | D65: C | F65: 950000 | G65: 1009000 | H65: 1107000 | I65: 1050000 | J65: 1104000 | K65: 1148000 | L65: 1085000 | M65: 878000 | N65: 1080000 | O65: 1161000 | P65: 1157000 | Q65: 1209000 | R65: =SUM(F65:Q65) -> 12938000
A66: 7122 | B66: Ventes de biens produits à l'étranger (export aéronautique) | C66: =VALUE(LEFT(A66,1)) -> 7 | D66: C | F66: 5383000 | G66: 5718000 | H66: 6275000 | I66: 5949000 | J66: 6255000 | K66: 6503000 | L66: 6148000 | M66: 4973000 | N66: 6123000 | O66: 6578000 | P66: 6556000 | Q66: 6850000 | R66: =SUM(F66:Q66) -> 73311000
A67: 7131 | B67: Variation des stocks de produits en cours (±) | C67: =VALUE(LEFT(A67,1)) -> 7 | D67: C | F67: -109000 | G67: 441000 | H67: -401000 | I67: -52000 | J67: 226000 | K67: 179000 | L67: 82000 | M67: 79000 | N67: -289000 | O67: 469000 | P67: -3000 | Q67: -172000 | R67: =SUM(F67:Q67) -> 450000
A68: 7132 | B68: Variation des stocks de biens produits (±) | C68: =VALUE(LEFT(A68,1)) -> 7 | D68: C | F68: 10000 | G68: -94000 | H68: 222000 | I68: -102000 | J68: 80000 | K68: -44000 | L68: 50000 | M68: -16000 | N68: 59000 | O68: -55000 | P68: -118000 | Q68: 236000 | R68: =SUM(F68:Q68) -> 228000
A69: 7142 | B69: Immobilisations corporelles produites (outillages) | C69: =VALUE(LEFT(A69,1)) -> 7 | D69: C | F69: 0 | G69: 0 | H69: 120000 | I69: 0 | J69: 0 | K69: 0 | L69: 0 | M69: 0 | N69: 95000 | O69: 0 | P69: 0 | Q69: 0 | R69: =SUM(F69:Q69) -> 215000
A70: 7161 | B70: Subventions d'exploitation reçues (formation) | C70: =VALUE(LEFT(A70,1)) -> 7 | D70: C | F70: 40000 | G70: 40000 | H70: 40000 | I70: 40000 | J70: 40000 | K70: 40000 | L70: 40000 | M70: 40000 | N70: 40000 | O70: 40000 | P70: 40000 | Q70: 40000 | R70: =SUM(F70:Q70) -> 480000
A71: 7196 | B71: Reprises sur provisions pour dépréciation de l'actif circulant | C71: =VALUE(LEFT(A71,1)) -> 7 | D71: C | F71: 0 | G71: 0 | H71: 0 | I71: 0 | J71: 0 | K71: 0 | L71: 0 | M71: 0 | N71: 0 | O71: 0 | P71: 0 | Q71: 35000 | R71: =SUM(F71:Q71) -> 35000
A72: 7197 | B72: Transferts de charges d'exploitation | C72: =VALUE(LEFT(A72,1)) -> 7 | D72: C | F72: 25000 | G72: 25000 | H72: 25000 | I72: 25000 | J72: 25000 | K72: 25000 | L72: 25000 | M72: 25000 | N72: 25000 | O72: 25000 | P72: 25000 | Q72: 25000 | R72: =SUM(F72:Q72) -> 300000
A73: 7331 | B73: Gains de change propres à l'exercice | C73: =VALUE(LEFT(A73,1)) -> 7 | D73: C | F73: 47000 | G73: 111000 | H73: 110000 | I73: 86000 | J73: 65000 | K73: 66000 | L73: 105000 | M73: 53000 | N73: 98000 | O73: 46000 | P73: 69000 | Q73: 105000 | R73: =SUM(F73:Q73) -> 961000
A74: 7381 | B74: Intérêts et produits assimilés | C74: =VALUE(LEFT(A74,1)) -> 7 | D74: C | F74: 5000 | G74: 5000 | H74: 5000 | I74: 5000 | J74: 5000 | K74: 5000 | L74: 5000 | M74: 5000 | N74: 5000 | O74: 5000 | P74: 5000 | Q74: 5000 | R74: =SUM(F74:Q74) -> 60000
A75: 7513 | B75: Produits des cessions des immobilisations corporelles | C75: =VALUE(LEFT(A75,1)) -> 7 | D75: C | F75: 0 | G75: 0 | H75: 0 | I75: 0 | J75: 0 | K75: 0 | L75: 0 | M75: 0 | N75: 0 | O75: 150000 | P75: 0 | Q75: 0 | R75: =SUM(F75:Q75) -> 150000
B77: Contrôle d'équilibre : total Débits − total Crédits (doit être égal à 0) | E77: =SUMPRODUCT(($D$6:$D$75="D")*($C$6:$C$75<=5)*E$6:E$75)-SUMPRODUCT(($D$6:$D$75="C")*($C$6:$C$75<=5)*E$6:E$75) -> 0 | F77: =SUMPRODUCT(($D$6:$D$75="D")*($C$6:$C$75<=5)*F$6:F$75)-SUMPRODUCT(($D$6:$D$75="C")*($C$6:$C$75<=5)*F$6:F$75)+SUMPRODUCT(($D$6:$D$75="D")*($C$6:$C$75>=6)*$F$6:F$75)-SUMPRODUCT(($D$6:$D$75="C")*($C$6:$C$75>=6)*$F$6:F$75) -> 0 | G77: =SUMPRODUCT(($D$6:$D$75="D")*($C$6:$C$75<=5)*G$6:G$75)-SUMPRODUCT(($D$6:$D$75="C")*($C$6:$C$75<=5)*G$6:G$75)+SUMPRODUCT(($D$6:$D$75="D")*($C$6:$C$75>=6)*$F$6:G$75)-SUMPRODUCT(($D$6:$D$75="C")*($C$6:$C$75>=6)*$F$6:G$75) -> 0 | H77: =SUMPRODUCT(($D$6:$D$75="D")*($C$6:$C$75<=5)*H$6:H$75)-SUMPRODUCT(($D$6:$D$75="C")*($C$6:$C$75<=5)*H$6:H$75)+SUMPRODUCT(($D$6:$D$75="D")*($C$6:$C$75>=6)*$F$6:H$75)-SUMPRODUCT(($D$6:$D$75="C")*($C$6:$C$75>=6)*$F$6:H$75) -> 0 | I77: =SUMPRODUCT(($D$6:$D$75="D")*($C$6:$C$75<=5)*I$6:I$75)-SUMPRODUCT(($D$6:$D$75="C")*($C$6:$C$75<=5)*I$6:I$75)+SUMPRODUCT(($D$6:$D$75="D")*($C$6:$C$75>=6)*$F$6:I$75)-SUMPRODUCT(($D$6:$D$75="C")*($C$6:$C$75>=6)*$F$6:I$75) -> 0 | J77: =SUMPRODUCT(($D$6:$D$75="D")*($C$6:$C$75<=5)*J$6:J$75)-SUMPRODUCT(($D$6:$D$75="C")*($C$6:$C$75<=5)*J$6:J$75)+SUMPRODUCT(($D$6:$D$75="D")*($C$6:$C$75>=6)*$F$6:J$75)-SUMPRODUCT(($D$6:$D$75="C")*($C$6:$C$75>=6)*$F$6:J$75) -> 0 | K77: =SUMPRODUCT(($D$6:$D$75="D")*($C$6:$C$75<=5)*K$6:K$75)-SUMPRODUCT(($D$6:$D$75="C")*($C$6:$C$75<=5)*K$6:K$75)+SUMPRODUCT(($D$6:$D$75="D")*($C$6:$C$75>=6)*$F$6:K$75)-SUMPRODUCT(($D$6:$D$75="C")*($C$6:$C$75>=6)*$F$6:K$75) -> 0 | L77: =SUMPRODUCT(($D$6:$D$75="D")*($C$6:$C$75<=5)*L$6:L$75)-SUMPRODUCT(($D$6:$D$75="C")*($C$6:$C$75<=5)*L$6:L$75)+SUMPRODUCT(($D$6:$D$75="D")*($C$6:$C$75>=6)*$F$6:L$75)-SUMPRODUCT(($D$6:$D$75="C")*($C$6:$C$75>=6)*$F$6:L$75) -> 0 | M77: =SUMPRODUCT(($D$6:$D$75="D")*($C$6:$C$75<=5)*M$6:M$75)-SUMPRODUCT(($D$6:$D$75="C")*($C$6:$C$75<=5)*M$6:M$75)+SUMPRODUCT(($D$6:$D$75="D")*($C$6:$C$75>=6)*$F$6:M$75)-SUMPRODUCT(($D$6:$D$75="C")*($C$6:$C$75>=6)*$F$6:M$75) -> 0 | ... Q77: =SUMPRODUCT(($D$6:$D$75="D")*($C$6:$C$75<=5)*Q$6:Q$75)-SUMPRODUCT(($D$6:$D$75="C")*($C$6:$C$75<=5)*Q$6:Q$75)+SUMPRODUCT(($D$6:$D$75="D")*($C$6:$C$75>=6)*$F$6:Q$75)-SUMPRODUCT(($D$6:$D$75="C")*($C$6:$C$75>=6)*$F$6:Q$75) -> 0
B80: DONNÉES DE RÉFÉRENCE N-1 (exercice 2022) — fictives
B81: Résultat net 2022 (même mois N-1) | F81: 345400 | G81: 689100 | H81: 731500 | I81: 579200 | J81: 791900 | K81: 494100 | L81: 757600 | M81: 195300 | N81: 625300 | O81: 1010900 | P81: 806900 | Q81: 795800 | R81: =SUM(F81:Q81) -> 7823000

Sheet CPC
A1: COMPTE DE PRODUITS ET CHARGES (CPC) — Modèle normal CGNC — 2023 | P1: ⌂ Accueil
A2: Montants en MAD · Calcul automatique mensuel depuis l'onglet Balance (SOMMEPROD par racine de compte) · Données fictives
A4: Réf. | B4: DÉSIGNATION | C4: Comptes | D4: Janvier | E4: Février | F4: Mars | G4: Avril | H4: Mai | I4: Juin | J4: Juillet | K4: Août | L4: Septembre | M4: Octobre | N4: Novembre | O4: Décembre | P4: Exercice 2023
A5: I | B5: PRODUITS D'EXPLOITATION
B6: Ventes de marchandises (en l'état) | C6: 711 | D6: =IFERROR(SUMPRODUCT((LEFT(Balance!$A$6:$A$75,3)="711")*Balance!F$6:F$75),0) -> 127000 | E6: =IFERROR(SUMPRODUCT((LEFT(Balance!$A$6:$A$75,3)="711")*Balance!G$6:G$75),0) -> 135000 | F6: =IFERROR(SUMPRODUCT((LEFT(Balance!$A$6:$A$75,3)="711")*Balance!H$6:H$75),0) -> 148000 | G6: =IFERROR(SUMPRODUCT((LEFT(Balance!$A$6:$A$75,3)="711")*Balance!I$6:I$75),0) -> 140000 | H6: =IFERROR(SUMPRODUCT((LEFT(Balance!$A$6:$A$75,3)="711")*Balance!J$6:J$75),0) -> 147000 | I6: =IFERROR(SUMPRODUCT((LEFT(Balance!$A$6:$A$75,3)="711")*Balance!K$6:K$75),0) -> 153000 | J6: =IFERROR(SUMPRODUCT((LEFT(Balance!$A$6:$A$75,3)="711")*Balance!L$6:L$75),0) -> 145000 | K6: =IFERROR(SUMPRODUCT((LEFT(Balance!$A$6:$A$75,3)="711")*Balance!M$6:M$75),0) -> 117000 | ... O6: =IFERROR(SUMPRODUCT((LEFT(Balance!$A$6:$A$75,3)="711")*Balance!Q$6:Q$75),0) -> 161000 | P6: =SUM(D6:O6) -> 1726000
B7: Ventes de biens et services produits | C7: 712 | D7: =IFERROR(SUMPRODUCT((LEFT(Balance!$A$6:$A$75,3)="712")*Balance!F$6:F$75),0) -> 6333000 | E7: =IFERROR(SUMPRODUCT((LEFT(Balance!$A$6:$A$75,3)="712")*Balance!G$6:G$75),0) -> 6727000 | F7: =IFERROR(SUMPRODUCT((LEFT(Balance!$A$6:$A$75,3)="712")*Balance!H$6:H$75),0) -> 7382000 | G7: =IFERROR(SUMPRODUCT((LEFT(Balance!$A$6:$A$75,3)="712")*Balance!I$6:I$75),0) -> 6999000 | H7: =IFERROR(SUMPRODUCT((LEFT(Balance!$A$6:$A$75,3)="712")*Balance!J$6:J$75),0) -> 7359000 | I7: =IFERROR(SUMPRODUCT((LEFT(Balance!$A$6:$A$75,3)="712")*Balance!K$6:K$75),0) -> 7651000 | J7: =IFERROR(SUMPRODUCT((LEFT(Balance!$A$6:$A$75,3)="712")*Balance!L$6:L$75),0) -> 7233000 | K7: =IFERROR(SUMPRODUCT((LEFT(Balance!$A$6:$A$75,3)="712")*Balance!M$6:M$75),0) -> 5851000 | ... O7: =IFERROR(SUMPRODUCT((LEFT(Balance!$A$6:$A$75,3)="712")*Balance!Q$6:Q$75),0) -> 8059000 | P7: =SUM(D7:O7) -> 86249000
B8: Chiffre d'affaires | D8: =D6+D7 -> 6460000 | E8: =E6+E7 -> 6862000 | F8: =F6+F7 -> 7530000 | G8: =G6+G7 -> 7139000 | H8: =H6+H7 -> 7506000 | I8: =I6+I7 -> 7804000 | J8: =J6+J7 -> 7378000 | K8: =K6+K7 -> 5968000 | ... O8: =O6+O7 -> 8220000 | P8: =SUM(D8:O8) -> 87975000
B9: Variation de stocks de produits (±) | C9: 713 | D9: =IFERROR(SUMPRODUCT((LEFT(Balance!$A$6:$A$75,3)="713")*Balance!F$6:F$75),0) -> -99000 | E9: =IFERROR(SUMPRODUCT((LEFT(Balance!$A$6:$A$75,3)="713")*Balance!G$6:G$75),0) -> 347000 | F9: =IFERROR(SUMPRODUCT((LEFT(Balance!$A$6:$A$75,3)="713")*Balance!H$6:H$75),0) -> -179000 | G9: =IFERROR(SUMPRODUCT((LEFT(Balance!$A$6:$A$75,3)="713")*Balance!I$6:I$75),0) -> -154000 | H9: =IFERROR(SUMPRODUCT((LEFT(Balance!$A$6:$A$75,3)="713")*Balance!J$6:J$75),0) -> 306000 | I9: =IFERROR(SUMPRODUCT((LEFT(Balance!$A$6:$A$75,3)="713")*Balance!K$6:K$75),0) -> 135000 | J9: =IFERROR(SUMPRODUCT((LEFT(Balance!$A$6:$A$75,3)="713")*Balance!L$6:L$75),0) -> 132000 | K9: =IFERROR(SUMPRODUCT((LEFT(Balance!$A$6:$A$75,3)="713")*Balance!M$6:M$75),0) -> 63000 | ... O9: =IFERROR(SUMPRODUCT((LEFT(Balance!$A$6:$A$75,3)="713")*Balance!Q$6:Q$75),0) -> 64000 | P9: =SUM(D9:O9) -> 678000
B10: Immobilisations produites par l'entreprise pour elle-même | C10: 714 | D10: =IFERROR(SUMPRODUCT((LEFT(Balance!$A$6:$A$75,3)="714")*Balance!F$6:F$75),0) -> 0 | E10: =IFERROR(SUMPRODUCT((LEFT(Balance!$A$6:$A$75,3)="714")*Balance!G$6:G$75),0) -> 0 | F10: =IFERROR(SUMPRODUCT((LEFT(Balance!$A$6:$A$75,3)="714")*Balance!H$6:H$75),0) -> 120000 | G10: =IFERROR(SUMPRODUCT((LEFT(Balance!$A$6:$A$75,3)="714")*Balance!I$6:I$75),0) -> 0 | H10: =IFERROR(SUMPRODUCT((LEFT(Balance!$A$6:$A$75,3)="714")*Balance!J$6:J$75),0) -> 0 | I10: =IFERROR(SUMPRODUCT((LEFT(Balance!$A$6:$A$75,3)="714")*Balance!K$6:K$75),0) -> 0 | J10: =IFERROR(SUMPRODUCT((LEFT(Balance!$A$6:$A$75,3)="714")*Balance!L$6:L$75),0) -> 0 | K10: =IFERROR(SUMPRODUCT((LEFT(Balance!$A$6:$A$75,3)="714")*Balance!M$6:M$75),0) -> 0 | ... O10: =IFERROR(SUMPRODUCT((LEFT(Balance!$A$6:$A$75,3)="714")*Balance!Q$6:Q$75),0) -> 0 | P10: =SUM(D10:O10) -> 215000
B11: Subventions d'exploitation | C11: 716 | D11: =IFERROR(SUMPRODUCT((LEFT(Balance!$A$6:$A$75,3)="716")*Balance!F$6:F$75),0) -> 40000 | E11: =IFERROR(SUMPRODUCT((LEFT(Balance!$A$6:$A$75,3)="716")*Balance!G$6:G$75),0) -> 40000 | F11: =IFERROR(SUMPRODUCT((LEFT(Balance!$A$6:$A$75,3)="716")*Balance!H$6:H$75),0) -> 40000 | G11: =IFERROR(SUMPRODUCT((LEFT(Balance!$A$6:$A$75,3)="716")*Balance!I$6:I$75),0) -> 40000 | H11: =IFERROR(SUMPRODUCT((LEFT(Balance!$A$6:$A$75,3)="716")*Balance!J$6:J$75),0) -> 40000 | I11: =IFERROR(SUMPRODUCT((LEFT(Balance!$A$6:$A$75,3)="716")*Balance!K$6:K$75),0) -> 40000 | J11: =IFERROR(SUMPRODUCT((LEFT(Balance!$A$6:$A$75,3)="716")*Balance!L$6:L$75),0) -> 40000 | K11: =IFERROR(SUMPRODUCT((LEFT(Balance!$A$6:$A$75,3)="716")*Balance!M$6:M$75),0) -> 40000 | ... O11: =IFERROR(SUMPRODUCT((LEFT(Balance!$A$6:$A$75,3)="716")*Balance!Q$6:Q$75),0) -> 40000 | P11: =SUM(D11:O11) -> 480000
B12: Autres produits d'exploitation | C12: 718 | D12: =IFERROR(SUMPRODUCT((LEFT(Balance!$A$6:$A$75,3)="718")*Balance!F$6:F$75),0) -> 0 | E12: =IFERROR(SUMPRODUCT((LEFT(Balance!$A$6:$A$75,3)="718")*Balance!G$6:G$75),0) -> 0 | F12: =IFERROR(SUMPRODUCT((LEFT(Balance!$A$6:$A$75,3)="718")*Balance!H$6:H$75),0) -> 0 | G12: =IFERROR(SUMPRODUCT((LEFT(Balance!$A$6:$A$75,3)="718")*Balance!I$6:I$75),0) -> 0 | H12: =IFERROR(SUMPRODUCT((LEFT(Balance!$A$6:$A$75,3)="718")*Balance!J$6:J$75),0) -> 0 | I12: =IFERROR(SUMPRODUCT((LEFT(Balance!$A$6:$A$75,3)="718")*Balance!K$6:K$75),0) -> 0 | J12: =IFERROR(SUMPRODUCT((LEFT(Balance!$A$6:$A$75,3)="718")*Balance!L$6:L$75),0) -> 0 | K12: =IFERROR(SUMPRODUCT((LEFT(Balance!$A$6:$A$75,3)="718")*Balance!M$6:M$75),0) -> 0 | ... O12: =IFERROR(SUMPRODUCT((LEFT(Balance!$A$6:$A$75,3)="718")*Balance!Q$6:Q$75),0) -> 0 | P12: =SUM(D12:O12) -> 0
B13: Reprises d'exploitation ; transferts de charges | C13: 719 | D13: =IFERROR(SUMPRODUCT((LEFT(Balance!$A$6:$A$75,3)="719")*Balance!F$6:F$75),0) -> 25000 | E13: =IFERROR(SUMPRODUCT((LEFT(Balance!$A$6:$A$75,3)="719")*Balance!G$6:G$75),0) -> 25000 | F13: =IFERROR(SUMPRODUCT((LEFT(Balance!$A$6:$A$75,3)="719")*Balance!H$6:H$75),0) -> 25000 | G13: =IFERROR(SUMPRODUCT((LEFT(Balance!$A$6:$A$75,3)="719")*Balance!I$6:I$75),0) -> 25000 | H13: =IFERROR(SUMPRODUCT((LEFT(Balance!$A$6:$A$75,3)="719")*Balance!J$6:J$75),0) -> 25000 | I13: =IFERROR(SUMPRODUCT((LEFT(Balance!$A$6:$A$75,3)="719")*Balance!K$6:K$75),0) -> 25000 | J13: =IFERROR(SUMPRODUCT((LEFT(Balance!$A$6:$A$75,3)="719")*Balance!L$6:L$75),0) -> 25000 | K13: =IFERROR(SUMPRODUCT((LEFT(Balance!$A$6:$A$75,3)="719")*Balance!M$6:M$75),0) -> 25000 | ... O13: =IFERROR(SUMPRODUCT((LEFT(Balance!$A$6:$A$75,3)="719")*Balance!Q$6:Q$75),0) -> 60000 | P13: =SUM(D13:O13) -> 335000
B14: TOTAL I | D14: =D8+D9+D10+D11+D12+D13 -> 6426000 | E14: =E8+E9+E10+E11+E12+E13 -> 7274000 | F14: =F8+F9+F10+F11+F12+F13 -> 7536000 | G14: =G8+G9+G10+G11+G12+G13 -> 7050000 | H14: =H8+H9+H10+H11+H12+H13 -> 7877000 | I14: =I8+I9+I10+I11+I12+I13 -> 8004000 | J14: =J8+J9+J10+J11+J12+J13 -> 7575000 | K14: =K8+K9+K10+K11+K12+K13 -> 6096000 | ... O14: =O8+O9+O10+O11+O12+O13 -> 8384000 | P14: =SUM(D14:O14) -> 89683000
A15: II | B15: CHARGES D'EXPLOITATION
B16: Achats revendus de marchandises | C16: 611 | D16: =IFERROR(SUMPRODUCT((LEFT(Balance!$A$6:$A$75,3)="611")*Balance!F$6:F$75),0) -> 94000 | E16: =IFERROR(SUMPRODUCT((LEFT(Balance!$A$6:$A$75,3)="611")*Balance!G$6:G$75),0) -> 100000 | F16: =IFERROR(SUMPRODUCT((LEFT(Balance!$A$6:$A$75,3)="611")*Balance!H$6:H$75),0) -> 110000 | G16: =IFERROR(SUMPRODUCT((LEFT(Balance!$A$6:$A$75,3)="611")*Balance!I$6:I$75),0) -> 104000 | H16: =IFERROR(SUMPRODUCT((LEFT(Balance!$A$6:$A$75,3)="611")*Balance!J$6:J$75),0) -> 109000 | I16: =IFERROR(SUMPRODUCT((LEFT(Balance!$A$6:$A$75,3)="611")*Balance!K$6:K$75),0) -> 113000 | J16: =IFERROR(SUMPRODUCT((LEFT(Balance!$A$6:$A$75,3)="611")*Balance!L$6:L$75),0) -> 107000 | K16: =IFERROR(SUMPRODUCT((LEFT(Balance!$A$6:$A$75,3)="611")*Balance!M$6:M$75),0) -> 87000 | ... O16: =IFERROR(SUMPRODUCT((LEFT(Balance!$A$6:$A$75,3)="611")*Balance!Q$6:Q$75),0) -> 119000 | P16: =SUM(D16:O16) -> 1279000
B17: Achats consommés de matières et fournitures | C17: 612 | D17: =IFERROR(SUMPRODUCT((LEFT(Balance!$A$6:$A$75,3)="612")*Balance!F$6:F$75),0) -> 3086000 | E17: =IFERROR(SUMPRODUCT((LEFT(Balance!$A$6:$A$75,3)="612")*Balance!G$6:G$75),0) -> 3502000 | F17: =IFERROR(SUMPRODUCT((LEFT(Balance!$A$6:$A$75,3)="612")*Balance!H$6:H$75),0) -> 3625000 | G17: =IFERROR(SUMPRODUCT((LEFT(Balance!$A$6:$A$75,3)="612")*Balance!I$6:I$75),0) -> 3388000 | H17: =IFERROR(SUMPRODUCT((LEFT(Balance!$A$6:$A$75,3)="612")*Balance!J$6:J$75),0) -> 3794000 | I17: =IFERROR(SUMPRODUCT((LEFT(Balance!$A$6:$A$75,3)="612")*Balance!K$6:K$75),0) -> 3855000 | J17: =IFERROR(SUMPRODUCT((LEFT(Balance!$A$6:$A$75,3)="612")*Balance!L$6:L$75),0) -> 3646000 | K17: =IFERROR(SUMPRODUCT((LEFT(Balance!$A$6:$A$75,3)="612")*Balance!M$6:M$75),0) -> 2927000 | ... O17: =IFERROR(SUMPRODUCT((LEFT(Balance!$A$6:$A$75,3)="612")*Balance!Q$6:Q$75),0) -> 4021000 | P17: =SUM(D17:O17) -> 43137000
B18: Autres charges externes | C18: 613 / 614 | D18: =IFERROR(SUMPRODUCT((LEFT(Balance!$A$6:$A$75,3)="613")*Balance!F$6:F$75)+SUMPRODUCT((LEFT(Balance!$A$6:$A$75,3)="614")*Balance!F$6:F$75),0) -> 422000 | E18: =IFERROR(SUMPRODUCT((LEFT(Balance!$A$6:$A$75,3)="613")*Balance!G$6:G$75)+SUMPRODUCT((LEFT(Balance!$A$6:$A$75,3)="614")*Balance!G$6:G$75),0) -> 442000 | F18: =IFERROR(SUMPRODUCT((LEFT(Balance!$A$6:$A$75,3)="613")*Balance!H$6:H$75)+SUMPRODUCT((LEFT(Balance!$A$6:$A$75,3)="614")*Balance!H$6:H$75),0) -> 458000 | G18: =IFERROR(SUMPRODUCT((LEFT(Balance!$A$6:$A$75,3)="613")*Balance!I$6:I$75)+SUMPRODUCT((LEFT(Balance!$A$6:$A$75,3)="614")*Balance!I$6:I$75),0) -> 444000 | H18: =IFERROR(SUMPRODUCT((LEFT(Balance!$A$6:$A$75,3)="613")*Balance!J$6:J$75)+SUMPRODUCT((LEFT(Balance!$A$6:$A$75,3)="614")*Balance!J$6:J$75),0) -> 552000 | I18: =IFERROR(SUMPRODUCT((LEFT(Balance!$A$6:$A$75,3)="613")*Balance!K$6:K$75)+SUMPRODUCT((LEFT(Balance!$A$6:$A$75,3)="614")*Balance!K$6:K$75),0) -> 889000 | J18: =IFERROR(SUMPRODUCT((LEFT(Balance!$A$6:$A$75,3)="613")*Balance!L$6:L$75)+SUMPRODUCT((LEFT(Balance!$A$6:$A$75,3)="614")*Balance!L$6:L$75),0) -> 455000 | K18: =IFERROR(SUMPRODUCT((LEFT(Balance!$A$6:$A$75,3)="613")*Balance!M$6:M$75)+SUMPRODUCT((LEFT(Balance!$A$6:$A$75,3)="614")*Balance!M$6:M$75),0) -> 408000 | ... O18: =IFERROR(SUMPRODUCT((LEFT(Balance!$A$6:$A$75,3)="613")*Balance!Q$6:Q$75)+SUMPRODUCT((LEFT(Balance!$A$6:$A$75,3)="614")*Balance!Q$6:Q$75),0) -> 482000 | P18: =SUM(D18:O18) -> 5946000
B19: Impôts et taxes | C19: 616 | D19: =IFERROR(SUMPRODUCT((LEFT(Balance!$A$6:$A$75,3)="616")*Balance!F$6:F$75),0) -> 25000 | E19: =IFERROR(SUMPRODUCT((LEFT(Balance!$A$6:$A$75,3)="616")*Balance!G$6:G$75),0) -> 25000 | F19: =IFERROR(SUMPRODUCT((LEFT(Balance!$A$6:$A$75,3)="616")*Balance!H$6:H$75),0) -> 25000 | G19: =IFERROR(SUMPRODUCT((LEFT(Balance!$A$6:$A$75,3)="616")*Balance!I$6:I$75),0) -> 25000 | H19: =IFERROR(SUMPRODUCT((LEFT(Balance!$A$6:$A$75,3)="616")*Balance!J$6:J$75),0) -> 25000 | I19: =IFERROR(SUMPRODUCT((LEFT(Balance!$A$6:$A$75,3)="616")*Balance!K$6:K$75),0) -> 25000 | J19: =IFERROR(SUMPRODUCT((LEFT(Balance!$A$6:$A$75,3)="616")*Balance!L$6:L$75),0) -> 25000 | K19: =IFERROR(SUMPRODUCT((LEFT(Balance!$A$6:$A$75,3)="616")*Balance!M$6:M$75),0) -> 25000 | ... O19: =IFERROR(SUMPRODUCT((LEFT(Balance!$A$6:$A$75,3)="616")*Balance!Q$6:Q$75),0) -> 25000 | P19: =SUM(D19:O19) -> 300000
B20: Charges de personnel | C20: 617 | D20: =IFERROR(SUMPRODUCT((LEFT(Balance!$A$6:$A$75,3)="617")*Balance!F$6:F$75),0) -> 1869000 | E20: =IFERROR(SUMPRODUCT((LEFT(Balance!$A$6:$A$75,3)="617")*Balance!G$6:G$75),0) -> 1876000 | F20: =IFERROR(SUMPRODUCT((LEFT(Balance!$A$6:$A$75,3)="617")*Balance!H$6:H$75),0) -> 1884000 | G20: =IFERROR(SUMPRODUCT((LEFT(Balance!$A$6:$A$75,3)="617")*Balance!I$6:I$75),0) -> 1891000 | H20: =IFERROR(SUMPRODUCT((LEFT(Balance!$A$6:$A$75,3)="617")*Balance!J$6:J$75),0) -> 1898000 | I20: =IFERROR(SUMPRODUCT((LEFT(Balance!$A$6:$A$75,3)="617")*Balance!K$6:K$75),0) -> 1906000 | J20: =IFERROR(SUMPRODUCT((LEFT(Balance!$A$6:$A$75,3)="617")*Balance!L$6:L$75),0) -> 1913000 | K20: =IFERROR(SUMPRODUCT((LEFT(Balance!$A$6:$A$75,3)="617")*Balance!M$6:M$75),0) -> 1921000 | ... O20: =IFERROR(SUMPRODUCT((LEFT(Balance!$A$6:$A$75,3)="617")*Balance!Q$6:Q$75),0) -> 2095000 | P20: =SUM(D20:O20) -> 23060000
B21: Autres charges d'exploitation | C21: 618 | D21: =IFERROR(SUMPRODUCT((LEFT(Balance!$A$6:$A$75,3)="618")*Balance!F$6:F$75),0) -> 0 | E21: =IFERROR(SUMPRODUCT((LEFT(Balance!$A$6:$A$75,3)="618")*Balance!G$6:G$75),0) -> 0 | F21: =IFERROR(SUMPRODUCT((LEFT(Balance!$A$6:$A$75,3)="618")*Balance!H$6:H$75),0) -> 0 | G21: =IFERROR(SUMPRODUCT((LEFT(Balance!$A$6:$A$75,3)="618")*Balance!I$6:I$75),0) -> 0 | H21: =IFERROR(SUMPRODUCT((LEFT(Balance!$A$6:$A$75,3)="618")*Balance!J$6:J$75),0) -> 0 | I21: =IFERROR(SUMPRODUCT((LEFT(Balance!$A$6:$A$75,3)="618")*Balance!K$6:K$75),0) -> 0 | J21: =IFERROR(SUMPRODUCT((LEFT(Balance!$A$6:$A$75,3)="618")*Balance!L$6:L$75),0) -> 0 | K21: =IFERROR(SUMPRODUCT((LEFT(Balance!$A$6:$A$75,3)="618")*Balance!M$6:M$75),0) -> 0 | ... O21: =IFERROR(SUMPRODUCT((LEFT(Balance!$A$6:$A$75,3)="618")*Balance!Q$6:Q$75),0) -> 35000 | P21: =SUM(D21:O21) -> 35000
B22: Dotations d'exploitation | C22: 619 | D22: =IFERROR(SUMPRODUCT((LEFT(Balance!$A$6:$A$75,3)="619")*Balance!F$6:F$75),0) -> 382500 | E22: =IFERROR(SUMPRODUCT((LEFT(Balance!$A$6:$A$75,3)="619")*Balance!G$6:G$75),0) -> 382500 | F22: =IFERROR(SUMPRODUCT((LEFT(Balance!$A$6:$A$75,3)="619")*Balance!H$6:H$75),0) -> 382500 | G22: =IFERROR(SUMPRODUCT((LEFT(Balance!$A$6:$A$75,3)="619")*Balance!I$6:I$75),0) -> 382500 | H22: =IFERROR(SUMPRODUCT((LEFT(Balance!$A$6:$A$75,3)="619")*Balance!J$6:J$75),0) -> 397500 | I22: =IFERROR(SUMPRODUCT((LEFT(Balance!$A$6:$A$75,3)="619")*Balance!K$6:K$75),0) -> 457500 | J22: =IFERROR(SUMPRODUCT((LEFT(Balance!$A$6:$A$75,3)="619")*Balance!L$6:L$75),0) -> 397500 | K22: =IFERROR(SUMPRODUCT((LEFT(Balance!$A$6:$A$75,3)="619")*Balance!M$6:M$75),0) -> 397500 | ... O22: =IFERROR(SUMPRODUCT((LEFT(Balance!$A$6:$A$75,3)="619")*Balance!Q$6:Q$75),0) -> 469500 | P22: =SUM(D22:O22) -> 4834000
B23: TOTAL II | D23: =D16+D17+D18+D19+D20+D21+D22 -> 5878500 | E23: =E16+E17+E18+E19+E20+E21+E22 -> 6327500 | F23: =F16+F17+F18+F19+F20+F21+F22 -> 6484500 | G23: =G16+G17+G18+G19+G20+G21+G22 -> 6234500 | H23: =H16+H17+H18+H19+H20+H21+H22 -> 6775500 | I23: =I16+I17+I18+I19+I20+I21+I22 -> 7245500 | J23: =J16+J17+J18+J19+J20+J21+J22 -> 6543500 | K23: =K16+K17+K18+K19+K20+K21+K22 -> 5765500 | ... O23: =O16+O17+O18+O19+O20+O21+O22 -> 7246500 | P23: =SUM(D23:O23) -> 78591000
B24: III. RÉSULTAT D'EXPLOITATION (I − II) | D24: =D14-D23 -> 547500 | E24: =E14-E23 -> 946500 | F24: =F14-F23 -> 1051500 | G24: =G14-G23 -> 815500 | H24: =H14-H23 -> 1101500 | I24: =I14-I23 -> 758500 | J24: =J14-J23 -> 1031500 | K24: =K14-K23 -> 330500 | ... O24: =O14-O23 -> 1137500 | P24: =SUM(D24:O24) -> 11092000
A25: IV | B25: PRODUITS FINANCIERS
B26: Produits des titres de participation et autres titres immobilisés | C26: 732 | D26: =IFERROR(SUMPRODUCT((LEFT(Balance!$A$6:$A$75,3)="732")*Balance!F$6:F$75),0) -> 0 | E26: =IFERROR(SUMPRODUCT((LEFT(Balance!$A$6:$A$75,3)="732")*Balance!G$6:G$75),0) -> 0 | F26: =IFERROR(SUMPRODUCT((LEFT(Balance!$A$6:$A$75,3)="732")*Balance!H$6:H$75),0) -> 0 | G26: =IFERROR(SUMPRODUCT((LEFT(Balance!$A$6:$A$75,3)="732")*Balance!I$6:I$75),0) -> 0 | H26: =IFERROR(SUMPRODUCT((LEFT(Balance!$A$6:$A$75,3)="732")*Balance!J$6:J$75),0) -> 0 | I26: =IFERROR(SUMPRODUCT((LEFT(Balance!$A$6:$A$75,3)="732")*Balance!K$6:K$75),0) -> 0 | J26: =IFERROR(SUMPRODUCT((LEFT(Balance!$A$6:$A$75,3)="732")*Balance!L$6:L$75),0) -> 0 | K26: =IFERROR(SUMPRODUCT((LEFT(Balance!$A$6:$A$75,3)="732")*Balance!M$6:M$75),0) -> 0 | ... O26: =IFERROR(SUMPRODUCT((LEFT(Balance!$A$6:$A$75,3)="732")*Balance!Q$6:Q$75),0) -> 0 | P26: =SUM(D26:O26) -> 0
B27: Gains de change | C27: 733 | D27: =IFERROR(SUMPRODUCT((LEFT(Balance!$A$6:$A$75,3)="733")*Balance!F$6:F$75),0) -> 47000 | E27: =IFERROR(SUMPRODUCT((LEFT(Balance!$A$6:$A$75,3)="733")*Balance!G$6:G$75),0) -> 111000 | F27: =IFERROR(SUMPRODUCT((LEFT(Balance!$A$6:$A$75,3)="733")*Balance!H$6:H$75),0) -> 110000 | G27: =IFERROR(SUMPRODUCT((LEFT(Balance!$A$6:$A$75,3)="733")*Balance!I$6:I$75),0) -> 86000 | H27: =IFERROR(SUMPRODUCT((LEFT(Balance!$A$6:$A$75,3)="733")*Balance!J$6:J$75),0) -> 65000 | I27: =IFERROR(SUMPRODUCT((LEFT(Balance!$A$6:$A$75,3)="733")*Balance!K$6:K$75),0) -> 66000 | J27: =IFERROR(SUMPRODUCT((LEFT(Balance!$A$6:$A$75,3)="733")*Balance!L$6:L$75),0) -> 105000 | K27: =IFERROR(SUMPRODUCT((LEFT(Balance!$A$6:$A$75,3)="733")*Balance!M$6:M$75),0) -> 53000 | ... O27: =IFERROR(SUMPRODUCT((LEFT(Balance!$A$6:$A$75,3)="733")*Balance!Q$6:Q$75),0) -> 105000 | P27: =SUM(D27:O27) -> 961000
B28: Intérêts et autres produits financiers | C28: 738 | D28: =IFERROR(SUMPRODUCT((LEFT(Balance!$A$6:$A$75,3)="738")*Balance!F$6:F$75),0) -> 5000 | E28: =IFERROR(SUMPRODUCT((LEFT(Balance!$A$6:$A$75,3)="738")*Balance!G$6:G$75),0) -> 5000 | F28: =IFERROR(SUMPRODUCT((LEFT(Balance!$A$6:$A$75,3)="738")*Balance!H$6:H$75),0) -> 5000 | G28: =IFERROR(SUMPRODUCT((LEFT(Balance!$A$6:$A$75,3)="738")*Balance!I$6:I$75),0) -> 5000 | H28: =IFERROR(SUMPRODUCT((LEFT(Balance!$A$6:$A$75,3)="738")*Balance!J$6:J$75),0) -> 5000 | I28: =IFERROR(SUMPRODUCT((LEFT(Balance!$A$6:$A$75,3)="738")*Balance!K$6:K$75),0) -> 5000 | J28: =IFERROR(SUMPRODUCT((LEFT(Balance!$A$6:$A$75,3)="738")*Balance!L$6:L$75),0) -> 5000 | K28: =IFERROR(SUMPRODUCT((LEFT(Balance!$A$6:$A$75,3)="738")*Balance!M$6:M$75),0) -> 5000 | ... O28: =IFERROR(SUMPRODUCT((LEFT(Balance!$A$6:$A$75,3)="738")*Balance!Q$6:Q$75),0) -> 5000 | P28: =SUM(D28:O28) -> 60000
B29: Reprises financières ; transferts de charges | C29: 739 | D29: =IFERROR(SUMPRODUCT((LEFT(Balance!$A$6:$A$75,3)="739")*Balance!F$6:F$75),0) -> 0 | E29: =IFERROR(SUMPRODUCT((LEFT(Balance!$A$6:$A$75,3)="739")*Balance!G$6:G$75),0) -> 0 | F29: =IFERROR(SUMPRODUCT((LEFT(Balance!$A$6:$A$75,3)="739")*Balance!H$6:H$75),0) -> 0 | G29: =IFERROR(SUMPRODUCT((LEFT(Balance!$A$6:$A$75,3)="739")*Balance!I$6:I$75),0) -> 0 | H29: =IFERROR(SUMPRODUCT((LEFT(Balance!$A$6:$A$75,3)="739")*Balance!J$6:J$75),0) -> 0 | I29: =IFERROR(SUMPRODUCT((LEFT(Balance!$A$6:$A$75,3)="739")*Balance!K$6:K$75),0) -> 0 | J29: =IFERROR(SUMPRODUCT((LEFT(Balance!$A$6:$A$75,3)="739")*Balance!L$6:L$75),0) -> 0 | K29: =IFERROR(SUMPRODUCT((LEFT(Balance!$A$6:$A$75,3)="739")*Balance!M$6:M$75),0) -> 0 | ... O29: =IFERROR(SUMPRODUCT((LEFT(Balance!$A$6:$A$75,3)="739")*Balance!Q$6:Q$75),0) -> 0 | P29: =SUM(D29:O29) -> 0
B30: TOTAL IV | D30: =D26+D27+D28+D29 -> 52000 | E30: =E26+E27+E28+E29 -> 116000 | F30: =F26+F27+F28+F29 -> 115000 | G30: =G26+G27+G28+G29 -> 91000 | H30: =H26+H27+H28+H29 -> 70000 | I30: =I26+I27+I28+I29 -> 71000 | J30: =J26+J27+J28+J29 -> 110000 | K30: =K26+K27+K28+K29 -> 58000 | ... O30: =O26+O27+O28+O29 -> 110000 | P30: =SUM(D30:O30) -> 1021000
A31: V | B31: CHARGES FINANCIÈRES
B32: Charges d'intérêts | C32: 631 | D32: =IFERROR(SUMPRODUCT((LEFT(Balance!$A$6:$A$75,3)="631")*Balance!F$6:F$75),0) -> 104000 | E32: =IFERROR(SUMPRODUCT((LEFT(Balance!$A$6:$A$75,3)="631")*Balance!G$6:G$75),0) -> 102700 | F32: =IFERROR(SUMPRODUCT((LEFT(Balance!$A$6:$A$75,3)="631")*Balance!H$6:H$75),0) -> 101400 | G32: =IFERROR(SUMPRODUCT((LEFT(Balance!$A$6:$A$75,3)="631")*Balance!I$6:I$75),0) -> 100100 | H32: =IFERROR(SUMPRODUCT((LEFT(Balance!$A$6:$A$75,3)="631")*Balance!J$6:J$75),0) -> 98800 | I32: =IFERROR(SUMPRODUCT((LEFT(Balance!$A$6:$A$75,3)="631")*Balance!K$6:K$75),0) -> 97500 | J32: =IFERROR(SUMPRODUCT((LEFT(Balance!$A$6:$A$75,3)="631")*Balance!L$6:L$75),0) -> 96200 | K32: =IFERROR(SUMPRODUCT((LEFT(Balance!$A$6:$A$75,3)="631")*Balance!M$6:M$75),0) -> 94900 | ... O32: =IFERROR(SUMPRODUCT((LEFT(Balance!$A$6:$A$75,3)="631")*Balance!Q$6:Q$75),0) -> 89700 | P32: =SUM(D32:O32) -> 1162200
B33: Pertes de change | C33: 633 | D33: =IFERROR(SUMPRODUCT((LEFT(Balance!$A$6:$A$75,3)="633")*Balance!F$6:F$75),0) -> 27000 | E33: =IFERROR(SUMPRODUCT((LEFT(Balance!$A$6:$A$75,3)="633")*Balance!G$6:G$75),0) -> 37000 | F33: =IFERROR(SUMPRODUCT((LEFT(Balance!$A$6:$A$75,3)="633")*Balance!H$6:H$75),0) -> 52000 | G33: =IFERROR(SUMPRODUCT((LEFT(Balance!$A$6:$A$75,3)="633")*Balance!I$6:I$75),0) -> 21000 | H33: =IFERROR(SUMPRODUCT((LEFT(Balance!$A$6:$A$75,3)="633")*Balance!J$6:J$75),0) -> 29000 | I33: =IFERROR(SUMPRODUCT((LEFT(Balance!$A$6:$A$75,3)="633")*Balance!K$6:K$75),0) -> 61000 | J33: =IFERROR(SUMPRODUCT((LEFT(Balance!$A$6:$A$75,3)="633")*Balance!L$6:L$75),0) -> 20000 | K33: =IFERROR(SUMPRODUCT((LEFT(Balance!$A$6:$A$75,3)="633")*Balance!M$6:M$75),0) -> 27000 | ... O33: =IFERROR(SUMPRODUCT((LEFT(Balance!$A$6:$A$75,3)="633")*Balance!Q$6:Q$75),0) -> 69000 | P33: =SUM(D33:O33) -> 458000
B34: Autres charges financières | C34: 638 | D34: =IFERROR(SUMPRODUCT((LEFT(Balance!$A$6:$A$75,3)="638")*Balance!F$6:F$75),0) -> 0 | E34: =IFERROR(SUMPRODUCT((LEFT(Balance!$A$6:$A$75,3)="638")*Balance!G$6:G$75),0) -> 0 | F34: =IFERROR(SUMPRODUCT((LEFT(Balance!$A$6:$A$75,3)="638")*Balance!H$6:H$75),0) -> 0 | G34: =IFERROR(SUMPRODUCT((LEFT(Balance!$A$6:$A$75,3)="638")*Balance!I$6:I$75),0) -> 0 | H34: =IFERROR(SUMPRODUCT((LEFT(Balance!$A$6:$A$75,3)="638")*Balance!J$6:J$75),0) -> 0 | I34: =IFERROR(SUMPRODUCT((LEFT(Balance!$A$6:$A$75,3)="638")*Balance!K$6:K$75),0) -> 0 | J34: =IFERROR(SUMPRODUCT((LEFT(Balance!$A$6:$A$75,3)="638")*Balance!L$6:L$75),0) -> 0 | K34: =IFERROR(SUMPRODUCT((LEFT(Balance!$A$6:$A$75,3)="638")*Balance!M$6:M$75),0) -> 0 | ... O34: =IFERROR(SUMPRODUCT((LEFT(Balance!$A$6:$A$75,3)="638")*Balance!Q$6:Q$75),0) -> 0 | P34: =SUM(D34:O34) -> 0
B35: Dotations financières | C35: 639 | D35: =IFERROR(SUMPRODUCT((LEFT(Balance!$A$6:$A$75,3)="639")*Balance!F$6:F$75),0) -> 0 | E35: =IFERROR(SUMPRODUCT((LEFT(Balance!$A$6:$A$75,3)="639")*Balance!G$6:G$75),0) -> 0 | F35: =IFERROR(SUMPRODUCT((LEFT(Balance!$A$6:$A$75,3)="639")*Balance!H$6:H$75),0) -> 0 | G35: =IFERROR(SUMPRODUCT((LEFT(Balance!$A$6:$A$75,3)="639")*Balance!I$6:I$75),0) -> 0 | H35: =IFERROR(SUMPRODUCT((LEFT(Balance!$A$6:$A$75,3)="639")*Balance!J$6:J$75),0) -> 0 | I35: =IFERROR(SUMPRODUCT((LEFT(Balance!$A$6:$A$75,3)="639")*Balance!K$6:K$75),0) -> 0 | J35: =IFERROR(SUMPRODUCT((LEFT(Balance!$A$6:$A$75,3)="639")*Balance!L$6:L$75),0) -> 0 | K35: =IFERROR(SUMPRODUCT((LEFT(Balance!$A$6:$A$75,3)="639")*Balance!M$6:M$75),0) -> 0 | ... O35: =IFERROR(SUMPRODUCT((LEFT(Balance!$A$6:$A$75,3)="639")*Balance!Q$6:Q$75),0) -> 0 | P35: =SUM(D35:O35) -> 0
B36: TOTAL V | D36: =D32+D33+D34+D35 -> 131000 | E36: =E32+E33+E34+E35 -> 139700 | F36: =F32+F33+F34+F35 -> 153400 | G36: =G32+G33+G34+G35 -> 121100 | H36: =H32+H33+H34+H35 -> 127800 | I36: =I32+I33+I34+I35 -> 158500 | J36: =J32+J33+J34+J35 -> 116200 | K36: =K32+K33+K34+K35 -> 121900 | ... O36: =O32+O33+O34+O35 -> 158700 | P36: =SUM(D36:O36) -> 1620200
B37: VI. RÉSULTAT FINANCIER (IV − V) | D37: =D30-D36 -> -79000 | E37: =E30-E36 -> -23700 | F37: =F30-F36 -> -38400 | G37: =G30-G36 -> -30100 | H37: =H30-H36 -> -57800 | I37: =I30-I36 -> -87500 | J37: =J30-J36 -> -6200 | K37: =K30-K36 -> -63900 | ... O37: =O30-O36 -> -48700 | P37: =SUM(D37:O37) -> -599200
B38: VII. RÉSULTAT COURANT (III + VI) | D38: =D24+D37 -> 468500 | E38: =E24+E37 -> 922800 | F38: =F24+F37 -> 1013100 | G38: =G24+G37 -> 785400 | H38: =H24+H37 -> 1043700 | I38: =I24+I37 -> 671000 | J38: =J24+J37 -> 1025300 | K38: =K24+K37 -> 266600 | ... O38: =O24+O37 -> 1088800 | P38: =SUM(D38:O38) -> 10492800
A39: VIII | B39: PRODUITS NON COURANTS
B40: Produits des cessions d'immobilisations | C40: 751 | D40: =IFERROR(SUMPRODUCT((LEFT(Balance!$A$6:$A$75,3)="751")*Balance!F$6:F$75),0) -> 0 | E40: =IFERROR(SUMPRODUCT((LEFT(Balance!$A$6:$A$75,3)="751")*Balance!G$6:G$75),0) -> 0 | F40: =IFERROR(SUMPRODUCT((LEFT(Balance!$A$6:$A$75,3)="751")*Balance!H$6:H$75),0) -> 0 | G40: =IFERROR(SUMPRODUCT((LEFT(Balance!$A$6:$A$75,3)="751")*Balance!I$6:I$75),0) -> 0 | H40: =IFERROR(SUMPRODUCT((LEFT(Balance!$A$6:$A$75,3)="751")*Balance!J$6:J$75),0) -> 0 | I40: =IFERROR(SUMPRODUCT((LEFT(Balance!$A$6:$A$75,3)="751")*Balance!K$6:K$75),0) -> 0 | J40: =IFERROR(SUMPRODUCT((LEFT(Balance!$A$6:$A$75,3)="751")*Balance!L$6:L$75),0) -> 0 | K40: =IFERROR(SUMPRODUCT((LEFT(Balance!$A$6:$A$75,3)="751")*Balance!M$6:M$75),0) -> 0 | ... O40: =IFERROR(SUMPRODUCT((LEFT(Balance!$A$6:$A$75,3)="751")*Balance!Q$6:Q$75),0) -> 0 | P40: =SUM(D40:O40) -> 150000
B41: Subventions d'équilibre | C41: 756 | D41: =IFERROR(SUMPRODUCT((LEFT(Balance!$A$6:$A$75,3)="756")*Balance!F$6:F$75),0) -> 0 | E41: =IFERROR(SUMPRODUCT((LEFT(Balance!$A$6:$A$75,3)="756")*Balance!G$6:G$75),0) -> 0 | F41: =IFERROR(SUMPRODUCT((LEFT(Balance!$A$6:$A$75,3)="756")*Balance!H$6:H$75),0) -> 0 | G41: =IFERROR(SUMPRODUCT((LEFT(Balance!$A$6:$A$75,3)="756")*Balance!I$6:I$75),0) -> 0 | H41: =IFERROR(SUMPRODUCT((LEFT(Balance!$A$6:$A$75,3)="756")*Balance!J$6:J$75),0) -> 0 | I41: =IFERROR(SUMPRODUCT((LEFT(Balance!$A$6:$A$75,3)="756")*Balance!K$6:K$75),0) -> 0 | J41: =IFERROR(SUMPRODUCT((LEFT(Balance!$A$6:$A$75,3)="756")*Balance!L$6:L$75),0) -> 0 | K41: =IFERROR(SUMPRODUCT((LEFT(Balance!$A$6:$A$75,3)="756")*Balance!M$6:M$75),0) -> 0 | ... O41: =IFERROR(SUMPRODUCT((LEFT(Balance!$A$6:$A$75,3)="756")*Balance!Q$6:Q$75),0) -> 0 | P41: =SUM(D41:O41) -> 0
B42: Reprises sur subventions d'investissement | C42: 757 | D42: =IFERROR(SUMPRODUCT((LEFT(Balance!$A$6:$A$75,3)="757")*Balance!F$6:F$75),0) -> 0 | E42: =IFERROR(SUMPRODUCT((LEFT(Balance!$A$6:$A$75,3)="757")*Balance!G$6:G$75),0) -> 0 | F42: =IFERROR(SUMPRODUCT((LEFT(Balance!$A$6:$A$75,3)="757")*Balance!H$6:H$75),0) -> 0 | G42: =IFERROR(SUMPRODUCT((LEFT(Balance!$A$6:$A$75,3)="757")*Balance!I$6:I$75),0) -> 0 | H42: =IFERROR(SUMPRODUCT((LEFT(Balance!$A$6:$A$75,3)="757")*Balance!J$6:J$75),0) -> 0 | I42: =IFERROR(SUMPRODUCT((LEFT(Balance!$A$6:$A$75,3)="757")*Balance!K$6:K$75),0) -> 0 | J42: =IFERROR(SUMPRODUCT((LEFT(Balance!$A$6:$A$75,3)="757")*Balance!L$6:L$75),0) -> 0 | K42: =IFERROR(SUMPRODUCT((LEFT(Balance!$A$6:$A$75,3)="757")*Balance!M$6:M$75),0) -> 0 | ... O42: =IFERROR(SUMPRODUCT((LEFT(Balance!$A$6:$A$75,3)="757")*Balance!Q$6:Q$75),0) -> 0 | P42: =SUM(D42:O42) -> 0
B43: Autres produits non courants | C43: 758 | D43: =IFERROR(SUMPRODUCT((LEFT(Balance!$A$6:$A$75,3)="758")*Balance!F$6:F$75),0) -> 0 | E43: =IFERROR(SUMPRODUCT((LEFT(Balance!$A$6:$A$75,3)="758")*Balance!G$6:G$75),0) -> 0 | F43: =IFERROR(SUMPRODUCT((LEFT(Balance!$A$6:$A$75,3)="758")*Balance!H$6:H$75),0) -> 0 | G43: =IFERROR(SUMPRODUCT((LEFT(Balance!$A$6:$A$75,3)="758")*Balance!I$6:I$75),0) -> 0 | H43: =IFERROR(SUMPRODUCT((LEFT(Balance!$A$6:$A$75,3)="758")*Balance!J$6:J$75),0) -> 0 | I43: =IFERROR(SUMPRODUCT((LEFT(Balance!$A$6:$A$75,3)="758")*Balance!K$6:K$75),0) -> 0 | J43: =IFERROR(SUMPRODUCT((LEFT(Balance!$A$6:$A$75,3)="758")*Balance!L$6:L$75),0) -> 0 | K43: =IFERROR(SUMPRODUCT((LEFT(Balance!$A$6:$A$75,3)="758")*Balance!M$6:M$75),0) -> 0 | ... O43: =IFERROR(SUMPRODUCT((LEFT(Balance!$A$6:$A$75,3)="758")*Balance!Q$6:Q$75),0) -> 0 | P43: =SUM(D43:O43) -> 0
B44: Reprises non courantes ; transferts de charges | C44: 759 | D44: =IFERROR(SUMPRODUCT((LEFT(Balance!$A$6:$A$75,3)="759")*Balance!F$6:F$75),0) -> 0 | E44: =IFERROR(SUMPRODUCT((LEFT(Balance!$A$6:$A$75,3)="759")*Balance!G$6:G$75),0) -> 0 | F44: =IFERROR(SUMPRODUCT((LEFT(Balance!$A$6:$A$75,3)="759")*Balance!H$6:H$75),0) -> 0 | G44: =IFERROR(SUMPRODUCT((LEFT(Balance!$A$6:$A$75,3)="759")*Balance!I$6:I$75),0) -> 0 | H44: =IFERROR(SUMPRODUCT((LEFT(Balance!$A$6:$A$75,3)="759")*Balance!J$6:J$75),0) -> 0 | I44: =IFERROR(SUMPRODUCT((LEFT(Balance!$A$6:$A$75,3)="759")*Balance!K$6:K$75),0) -> 0 | J44: =IFERROR(SUMPRODUCT((LEFT(Balance!$A$6:$A$75,3)="759")*Balance!L$6:L$75),0) -> 0 | K44: =IFERROR(SUMPRODUCT((LEFT(Balance!$A$6:$A$75,3)="759")*Balance!M$6:M$75),0) -> 0 | ... O44: =IFERROR(SUMPRODUCT((LEFT(Balance!$A$6:$A$75,3)="759")*Balance!Q$6:Q$75),0) -> 0 | P44: =SUM(D44:O44) -> 0
B45: TOTAL VIII | D45: =D40+D41+D42+D43+D44 -> 0 | E45: =E40+E41+E42+E43+E44 -> 0 | F45: =F40+F41+F42+F43+F44 -> 0 | G45: =G40+G41+G42+G43+G44 -> 0 | H45: =H40+H41+H42+H43+H44 -> 0 | I45: =I40+I41+I42+I43+I44 -> 0 | J45: =J40+J41+J42+J43+J44 -> 0 | K45: =K40+K41+K42+K43+K44 -> 0 | ... O45: =O40+O41+O42+O43+O44 -> 0 | P45: =SUM(D45:O45) -> 150000
A46: IX | B46: CHARGES NON COURANTES
B47: Valeurs nettes d'amortissements des immobilisations cédées | C47: 651 | D47: =IFERROR(SUMPRODUCT((LEFT(Balance!$A$6:$A$75,3)="651")*Balance!F$6:F$75),0) -> 0 | E47: =IFERROR(SUMPRODUCT((LEFT(Balance!$A$6:$A$75,3)="651")*Balance!G$6:G$75),0) -> 0 | F47: =IFERROR(SUMPRODUCT((LEFT(Balance!$A$6:$A$75,3)="651")*Balance!H$6:H$75),0) -> 0 | G47: =IFERROR(SUMPRODUCT((LEFT(Balance!$A$6:$A$75,3)="651")*Balance!I$6:I$75),0) -> 0 | H47: =IFERROR(SUMPRODUCT((LEFT(Balance!$A$6:$A$75,3)="651")*Balance!J$6:J$75),0) -> 0 | I47: =IFERROR(SUMPRODUCT((LEFT(Balance!$A$6:$A$75,3)="651")*Balance!K$6:K$75),0) -> 0 | J47: =IFERROR(SUMPRODUCT((LEFT(Balance!$A$6:$A$75,3)="651")*Balance!L$6:L$75),0) -> 0 | K47: =IFERROR(SUMPRODUCT((LEFT(Balance!$A$6:$A$75,3)="651")*Balance!M$6:M$75),0) -> 0 | ... O47: =IFERROR(SUMPRODUCT((LEFT(Balance!$A$6:$A$75,3)="651")*Balance!Q$6:Q$75),0) -> 0 | P47: =SUM(D47:O47) -> 110000
B48: Subventions accordées | C48: 656 | D48: =IFERROR(SUMPRODUCT((LEFT(Balance!$A$6:$A$75,3)="656")*Balance!F$6:F$75),0) -> 0 | E48: =IFERROR(SUMPRODUCT((LEFT(Balance!$A$6:$A$75,3)="656")*Balance!G$6:G$75),0) -> 0 | F48: =IFERROR(SUMPRODUCT((LEFT(Balance!$A$6:$A$75,3)="656")*Balance!H$6:H$75),0) -> 0 | G48: =IFERROR(SUMPRODUCT((LEFT(Balance!$A$6:$A$75,3)="656")*Balance!I$6:I$75),0) -> 0 | H48: =IFERROR(SUMPRODUCT((LEFT(Balance!$A$6:$A$75,3)="656")*Balance!J$6:J$75),0) -> 0 | I48: =IFERROR(SUMPRODUCT((LEFT(Balance!$A$6:$A$75,3)="656")*Balance!K$6:K$75),0) -> 0 | J48: =IFERROR(SUMPRODUCT((LEFT(Balance!$A$6:$A$75,3)="656")*Balance!L$6:L$75),0) -> 0 | K48: =IFERROR(SUMPRODUCT((LEFT(Balance!$A$6:$A$75,3)="656")*Balance!M$6:M$75),0) -> 0 | ... O48: =IFERROR(SUMPRODUCT((LEFT(Balance!$A$6:$A$75,3)="656")*Balance!Q$6:Q$75),0) -> 0 | P48: =SUM(D48:O48) -> 0
B49: Autres charges non courantes | C49: 658 | D49: =IFERROR(SUMPRODUCT((LEFT(Balance!$A$6:$A$75,3)="658")*Balance!F$6:F$75),0) -> 0 | E49: =IFERROR(SUMPRODUCT((LEFT(Balance!$A$6:$A$75,3)="658")*Balance!G$6:G$75),0) -> 0 | F49: =IFERROR(SUMPRODUCT((LEFT(Balance!$A$6:$A$75,3)="658")*Balance!H$6:H$75),0) -> 20000 | G49: =IFERROR(SUMPRODUCT((LEFT(Balance!$A$6:$A$75,3)="658")*Balance!I$6:I$75),0) -> 0 | H49: =IFERROR(SUMPRODUCT((LEFT(Balance!$A$6:$A$75,3)="658")*Balance!J$6:J$75),0) -> 0 | I49: =IFERROR(SUMPRODUCT((LEFT(Balance!$A$6:$A$75,3)="658")*Balance!K$6:K$75),0) -> 0 | J49: =IFERROR(SUMPRODUCT((LEFT(Balance!$A$6:$A$75,3)="658")*Balance!L$6:L$75),0) -> 0 | K49: =IFERROR(SUMPRODUCT((LEFT(Balance!$A$6:$A$75,3)="658")*Balance!M$6:M$75),0) -> 0 | ... O49: =IFERROR(SUMPRODUCT((LEFT(Balance!$A$6:$A$75,3)="658")*Balance!Q$6:Q$75),0) -> 0 | P49: =SUM(D49:O49) -> 20000
B50: Dotations non courantes aux amortissements et aux provisions | C50: 659 | D50: =IFERROR(SUMPRODUCT((LEFT(Balance!$A$6:$A$75,3)="659")*Balance!F$6:F$75),0) -> 0 | E50: =IFERROR(SUMPRODUCT((LEFT(Balance!$A$6:$A$75,3)="659")*Balance!G$6:G$75),0) -> 0 | F50: =IFERROR(SUMPRODUCT((LEFT(Balance!$A$6:$A$75,3)="659")*Balance!H$6:H$75),0) -> 0 | G50: =IFERROR(SUMPRODUCT((LEFT(Balance!$A$6:$A$75,3)="659")*Balance!I$6:I$75),0) -> 0 | H50: =IFERROR(SUMPRODUCT((LEFT(Balance!$A$6:$A$75,3)="659")*Balance!J$6:J$75),0) -> 0 | I50: =IFERROR(SUMPRODUCT((LEFT(Balance!$A$6:$A$75,3)="659")*Balance!K$6:K$75),0) -> 0 | J50: =IFERROR(SUMPRODUCT((LEFT(Balance!$A$6:$A$75,3)="659")*Balance!L$6:L$75),0) -> 0 | K50: =IFERROR(SUMPRODUCT((LEFT(Balance!$A$6:$A$75,3)="659")*Balance!M$6:M$75),0) -> 0 | ... O50: =IFERROR(SUMPRODUCT((LEFT(Balance!$A$6:$A$75,3)="659")*Balance!Q$6:Q$75),0) -> 0 | P50: =SUM(D50:O50) -> 0
B51: TOTAL IX | D51: =D47+D48+D49+D50 -> 0 | E51: =E47+E48+E49+E50 -> 0 | F51: =F47+F48+F49+F50 -> 20000 | G51: =G47+G48+G49+G50 -> 0 | H51: =H47+H48+H49+H50 -> 0 | I51: =I47+I48+I49+I50 -> 0 | J51: =J47+J48+J49+J50 -> 0 | K51: =K47+K48+K49+K50 -> 0 | ... O51: =O47+O48+O49+O50 -> 0 | P51: =SUM(D51:O51) -> 130000
B52: X. RÉSULTAT NON COURANT (VIII − IX) | D52: =D45-D51 -> 0 | E52: =E45-E51 -> 0 | F52: =F45-F51 -> -20000 | G52: =G45-G51 -> 0 | H52: =H45-H51 -> 0 | I52: =I45-I51 -> 0 | J52: =J45-J51 -> 0 | K52: =K45-K51 -> 0 | ... O52: =O45-O51 -> 0 | P52: =SUM(D52:O52) -> 20000
B53: XI. RÉSULTAT AVANT IMPÔTS (VII + X) | D53: =D38+D52 -> 468500 | E53: =E38+E52 -> 922800 | F53: =F38+F52 -> 993100 | G53: =G38+G52 -> 785400 | H53: =H38+H52 -> 1043700 | I53: =I38+I52 -> 671000 | J53: =J38+J52 -> 1025300 | K53: =K38+K52 -> 266600 | ... O53: =O38+O52 -> 1088800 | P53: =SUM(D53:O53) -> 10512800
B54: XII. IMPÔTS SUR LES RÉSULTATS | C54: 670 | D54: =IFERROR(SUMPRODUCT((LEFT(Balance!$A$6:$A$75,3)="670")*Balance!F$6:F$75),0) -> 93700 | E54: =IFERROR(SUMPRODUCT((LEFT(Balance!$A$6:$A$75,3)="670")*Balance!G$6:G$75),0) -> 184600 | F54: =IFERROR(SUMPRODUCT((LEFT(Balance!$A$6:$A$75,3)="670")*Balance!H$6:H$75),0) -> 198600 | G54: =IFERROR(SUMPRODUCT((LEFT(Balance!$A$6:$A$75,3)="670")*Balance!I$6:I$75),0) -> 157100 | H54: =IFERROR(SUMPRODUCT((LEFT(Balance!$A$6:$A$75,3)="670")*Balance!J$6:J$75),0) -> 208700 | I54: =IFERROR(SUMPRODUCT((LEFT(Balance!$A$6:$A$75,3)="670")*Balance!K$6:K$75),0) -> 134200 | J54: =IFERROR(SUMPRODUCT((LEFT(Balance!$A$6:$A$75,3)="670")*Balance!L$6:L$75),0) -> 205100 | K54: =IFERROR(SUMPRODUCT((LEFT(Balance!$A$6:$A$75,3)="670")*Balance!M$6:M$75),0) -> 53300 | ... O54: =IFERROR(SUMPRODUCT((LEFT(Balance!$A$6:$A$75,3)="670")*Balance!Q$6:Q$75),0) -> 217800 | P54: =SUM(D54:O54) -> 2102600
B55: XIII. RÉSULTAT NET (XI − XII) | D55: =D53-D54 -> 374800 | E55: =E53-E54 -> 738200 | F55: =F53-F54 -> 794500 | G55: =G53-G54 -> 628300 | H55: =H53-H54 -> 835000 | I55: =I53-I54 -> 536800 | J55: =J53-J54 -> 820200 | K55: =K53-K54 -> 213300 | ... O55: =O53-O54 -> 871000 | P55: =SUM(D55:O55) -> 8410200
B56: XIV. TOTAL DES PRODUITS (I + IV + VIII) | D56: =D14+D30+D45 -> 6478000 | E56: =E14+E30+E45 -> 7390000 | F56: =F14+F30+F45 -> 7651000 | G56: =G14+G30+G45 -> 7141000 | H56: =H14+H30+H45 -> 7947000 | I56: =I14+I30+I45 -> 8075000 | J56: =J14+J30+J45 -> 7685000 | K56: =K14+K30+K45 -> 6154000 | ... O56: =O14+O30+O45 -> 8494000 | P56: =SUM(D56:O56) -> 90854000
B57: XV. TOTAL DES CHARGES (II + V + IX + XII) | D57: =D23+D36+D51+D54 -> 6103200 | E57: =E23+E36+E51+E54 -> 6651800 | F57: =F23+F36+F51+F54 -> 6856500 | G57: =G23+G36+G51+G54 -> 6512700 | H57: =H23+H36+H51+H54 -> 7112000 | I57: =I23+I36+I51+I54 -> 7538200 | J57: =J23+J36+J51+J54 -> 6864800 | K57: =K23+K36+K51+K54 -> 5940700 | ... O57: =O23+O36+O51+O54 -> 7623000 | P57: =SUM(D57:O57) -> 82443800
B58: XIII. RÉSULTAT NET (XIV − XV) — contrôle | D58: =D56-D57 -> 374800 | E58: =E56-E57 -> 738200 | F58: =F56-F57 -> 794500 | G58: =G56-G57 -> 628300 | H58: =H56-H57 -> 835000 | I58: =I56-I57 -> 536800 | J58: =J56-J57 -> 820200 | K58: =K56-K57 -> 213300 | ... O58: =O56-O57 -> 871000 | P58: =SUM(D58:O58) -> 8410200
B60: Contrôle : écart entre les deux calculs du résultat net (doit être 0) | D60: =D55-D58 -> 0 | E60: =E55-E58 -> 0 | F60: =F55-F58 -> 0 | G60: =G55-G58 -> 0 | H60: =H55-H58 -> 0 | I60: =I55-I58 -> 0 | J60: =J55-J58 -> 0 | K60: =K55-K58 -> 0 | ... P60: =P55-P58 -> 0

Sheet ESG
A1: ÉTAT DES SOLDES DE GESTION (ESG) — CGNC — 2023 | P1: ⌂ Accueil
A2: Montants en MAD · Calcul automatique mensuel depuis le CPC et la Balance · Données fictives
A4: Réf. | B4: DÉSIGNATION | C4: Source | D4: Janvier | E4: Février | F4: Mars | G4: Avril | H4: Mai | I4: Juin | J4: Juillet | K4: Août | L4: Septembre | M4: Octobre | N4: Novembre | O4: Décembre | P4: Exercice 2023
A5: A | B5: TABLEAU DE FORMATION DES RÉSULTATS (TFR)
B6: 1. Ventes de marchandises (en l'état) | C6: CPC | D6: =CPC!D6 -> 127000 | E6: =CPC!E6 -> 135000 | F6: =CPC!F6 -> 148000 | G6: =CPC!G6 -> 140000 | H6: =CPC!H6 -> 147000 | I6: =CPC!I6 -> 153000 | J6: =CPC!J6 -> 145000 | K6: =CPC!K6 -> 117000 | ... O6: =CPC!O6 -> 161000 | P6: =SUM(D6:O6) -> 1726000
B7: 2. − Achats revendus de marchandises | C7: CPC | D7: =CPC!D16 -> 94000 | E7: =CPC!E16 -> 100000 | F7: =CPC!F16 -> 110000 | G7: =CPC!G16 -> 104000 | H7: =CPC!H16 -> 109000 | I7: =CPC!I16 -> 113000 | J7: =CPC!J16 -> 107000 | K7: =CPC!K16 -> 87000 | ... O7: =CPC!O16 -> 119000 | P7: =SUM(D7:O7) -> 1279000
B8: I. = MARGE BRUTE SUR VENTES EN L'ÉTAT | D8: =D6-D7 -> 33000 | E8: =E6-E7 -> 35000 | F8: =F6-F7 -> 38000 | G8: =G6-G7 -> 36000 | H8: =H6-H7 -> 38000 | I8: =I6-I7 -> 40000 | J8: =J6-J7 -> 38000 | K8: =K6-K7 -> 30000 | ... O8: =O6-O7 -> 42000 | P8: =SUM(D8:O8) -> 447000
B9: 3. Ventes de biens et services produits | C9: CPC | D9: =CPC!D7 -> 6333000 | E9: =CPC!E7 -> 6727000 | F9: =CPC!F7 -> 7382000 | G9: =CPC!G7 -> 6999000 | H9: =CPC!H7 -> 7359000 | I9: =CPC!I7 -> 7651000 | J9: =CPC!J7 -> 7233000 | K9: =CPC!K7 -> 5851000 | ... O9: =CPC!O7 -> 8059000 | P9: =SUM(D9:O9) -> 86249000
B10: 4. Variation de stocks de produits (±) | C10: CPC | D10: =CPC!D9 -> -99000 | E10: =CPC!E9 -> 347000 | F10: =CPC!F9 -> -179000 | G10: =CPC!G9 -> -154000 | H10: =CPC!H9 -> 306000 | I10: =CPC!I9 -> 135000 | J10: =CPC!J9 -> 132000 | K10: =CPC!K9 -> 63000 | ... O10: =CPC!O9 -> 64000 | P10: =SUM(D10:O10) -> 678000
B11: 5. Immobilisations produites par l'entreprise pour elle-même | C11: CPC | D11: =CPC!D10 -> 0 | E11: =CPC!E10 -> 0 | F11: =CPC!F10 -> 120000 | G11: =CPC!G10 -> 0 | H11: =CPC!H10 -> 0 | I11: =CPC!I10 -> 0 | J11: =CPC!J10 -> 0 | K11: =CPC!K10 -> 0 | ... O11: =CPC!O10 -> 0 | P11: =SUM(D11:O11) -> 215000
B12: II. + PRODUCTION DE L'EXERCICE (3 + 4 + 5) | D12: =D9+D10+D11 -> 6234000 | E12: =E9+E10+E11 -> 7074000 | F12: =F9+F10+F11 -> 7323000 | G12: =G9+G10+G11 -> 6845000 | H12: =H9+H10+H11 -> 7665000 | I12: =I9+I10+I11 -> 7786000 | J12: =J9+J10+J11 -> 7365000 | K12: =K9+K10+K11 -> 5914000 | ... O12: =O9+O10+O11 -> 8123000 | P12: =SUM(D12:O12) -> 87142000
B13: 6. Achats consommés de matières et fournitures | C13: CPC | D13: =CPC!D17 -> 3086000 | E13: =CPC!E17 -> 3502000 | F13: =CPC!F17 -> 3625000 | G13: =CPC!G17 -> 3388000 | H13: =CPC!H17 -> 3794000 | I13: =CPC!I17 -> 3855000 | J13: =CPC!J17 -> 3646000 | K13: =CPC!K17 -> 2927000 | ... O13: =CPC!O17 -> 4021000 | P13: =SUM(D13:O13) -> 43137000
B14: 7. Autres charges externes | C14: CPC | D14: =CPC!D18 -> 422000 | E14: =CPC!E18 -> 442000 | F14: =CPC!F18 -> 458000 | G14: =CPC!G18 -> 444000 | H14: =CPC!H18 -> 552000 | I14: =CPC!I18 -> 889000 | J14: =CPC!J18 -> 455000 | K14: =CPC!K18 -> 408000 | ... O14: =CPC!O18 -> 482000 | P14: =SUM(D14:O14) -> 5946000
B15: III. − CONSOMMATION DE L'EXERCICE (6 + 7) | D15: =D13+D14 -> 3508000 | E15: =E13+E14 -> 3944000 | F15: =F13+F14 -> 4083000 | G15: =G13+G14 -> 3832000 | H15: =H13+H14 -> 4346000 | I15: =I13+I14 -> 4744000 | J15: =J13+J14 -> 4101000 | K15: =K13+K14 -> 3335000 | ... O15: =O13+O14 -> 4503000 | P15: =SUM(D15:O15) -> 49083000
B16: IV. = VALEUR AJOUTÉE (I + II − III) | D16: =D8+D12-D15 -> 2759000 | E16: =E8+E12-E15 -> 3165000 | F16: =F8+F12-F15 -> 3278000 | G16: =G8+G12-G15 -> 3049000 | H16: =H8+H12-H15 -> 3357000 | I16: =I8+I12-I15 -> 3082000 | J16: =J8+J12-J15 -> 3302000 | K16: =K8+K12-K15 -> 2609000 | ... O16: =O8+O12-O15 -> 3662000 | P16: =SUM(D16:O16) -> 38506000
B17: 8. + Subventions d'exploitation | C17: CPC | D17: =CPC!D11 -> 40000 | E17: =CPC!E11 -> 40000 | F17: =CPC!F11 -> 40000 | G17: =CPC!G11 -> 40000 | H17: =CPC!H11 -> 40000 | I17: =CPC!I11 -> 40000 | J17: =CPC!J11 -> 40000 | K17: =CPC!K11 -> 40000 | ... O17: =CPC!O11 -> 40000 | P17: =SUM(D17:O17) -> 480000
B18: 9. − Impôts et taxes | C18: CPC | D18: =CPC!D19 -> 25000 | E18: =CPC!E19 -> 25000 | F18: =CPC!F19 -> 25000 | G18: =CPC!G19 -> 25000 | H18: =CPC!H19 -> 25000 | I18: =CPC!I19 -> 25000 | J18: =CPC!J19 -> 25000 | K18: =CPC!K19 -> 25000 | ... O18: =CPC!O19 -> 25000 | P18: =SUM(D18:O18) -> 300000
B19: 10. − Charges de personnel | C19: CPC | D19: =CPC!D20 -> 1869000 | E19: =CPC!E20 -> 1876000 | F19: =CPC!F20 -> 1884000 | G19: =CPC!G20 -> 1891000 | H19: =CPC!H20 -> 1898000 | I19: =CPC!I20 -> 1906000 | J19: =CPC!J20 -> 1913000 | K19: =CPC!K20 -> 1921000 | ... O19: =CPC!O20 -> 2095000 | P19: =SUM(D19:O19) -> 23060000
B20: V. = EXCÉDENT BRUT D'EXPLOITATION (EBE) ou INSUFFISANCE (IBE) | D20: =D16+D17-D18-D19 -> 905000 | E20: =E16+E17-E18-E19 -> 1304000 | F20: =F16+F17-F18-F19 -> 1409000 | G20: =G16+G17-G18-G19 -> 1173000 | H20: =H16+H17-H18-H19 -> 1474000 | I20: =I16+I17-I18-I19 -> 1191000 | J20: =J16+J17-J18-J19 -> 1404000 | K20: =K16+K17-K18-K19 -> 703000 | ... O20: =O16+O17-O18-O19 -> 1582000 | P20: =SUM(D20:O20) -> 15626000
B21: 11. + Autres produits d'exploitation | C21: CPC | D21: =CPC!D12 -> 0 | E21: =CPC!E12 -> 0 | F21: =CPC!F12 -> 0 | G21: =CPC!G12 -> 0 | H21: =CPC!H12 -> 0 | I21: =CPC!I12 -> 0 | J21: =CPC!J12 -> 0 | K21: =CPC!K12 -> 0 | ... O21: =CPC!O12 -> 0 | P21: =SUM(D21:O21) -> 0
B22: 12. − Autres charges d'exploitation | C22: CPC | D22: =CPC!D21 -> 0 | E22: =CPC!E21 -> 0 | F22: =CPC!F21 -> 0 | G22: =CPC!G21 -> 0 | H22: =CPC!H21 -> 0 | I22: =CPC!I21 -> 0 | J22: =CPC!J21 -> 0 | K22: =CPC!K21 -> 0 | ... O22: =CPC!O21 -> 35000 | P22: =SUM(D22:O22) -> 35000
B23: 13. + Reprises d'exploitation, transferts de charges | C23: CPC | D23: =CPC!D13 -> 25000 | E23: =CPC!E13 -> 25000 | F23: =CPC!F13 -> 25000 | G23: =CPC!G13 -> 25000 | H23: =CPC!H13 -> 25000 | I23: =CPC!I13 -> 25000 | J23: =CPC!J13 -> 25000 | K23: =CPC!K13 -> 25000 | ... O23: =CPC!O13 -> 60000 | P23: =SUM(D23:O23) -> 335000
B24: 14. − Dotations d'exploitation | C24: CPC | D24: =CPC!D22 -> 382500 | E24: =CPC!E22 -> 382500 | F24: =CPC!F22 -> 382500 | G24: =CPC!G22 -> 382500 | H24: =CPC!H22 -> 397500 | I24: =CPC!I22 -> 457500 | J24: =CPC!J22 -> 397500 | K24: =CPC!K22 -> 397500 | ... O24: =CPC!O22 -> 469500 | P24: =SUM(D24:O24) -> 4834000
B25: VI. = RÉSULTAT D'EXPLOITATION (+ ou −) | D25: =D20+D21-D22+D23-D24 -> 547500 | E25: =E20+E21-E22+E23-E24 -> 946500 | F25: =F20+F21-F22+F23-F24 -> 1051500 | G25: =G20+G21-G22+G23-G24 -> 815500 | H25: =H20+H21-H22+H23-H24 -> 1101500 | I25: =I20+I21-I22+I23-I24 -> 758500 | J25: =J20+J21-J22+J23-J24 -> 1031500 | K25: =K20+K21-K22+K23-K24 -> 330500 | ... O25: =O20+O21-O22+O23-O24 -> 1137500 | P25: =SUM(D25:O25) -> 11092000
B26: VII. ± RÉSULTAT FINANCIER | C26: CPC | D26: =CPC!D37 -> -79000 | E26: =CPC!E37 -> -23700 | F26: =CPC!F37 -> -38400 | G26: =CPC!G37 -> -30100 | H26: =CPC!H37 -> -57800 | I26: =CPC!I37 -> -87500 | J26: =CPC!J37 -> -6200 | K26: =CPC!K37 -> -63900 | ... O26: =CPC!O37 -> -48700 | P26: =SUM(D26:O26) -> -599200
B27: VIII. = RÉSULTAT COURANT (+ ou −) | D27: =D25+D26 -> 468500 | E27: =E25+E26 -> 922800 | F27: =F25+F26 -> 1013100 | G27: =G25+G26 -> 785400 | H27: =H25+H26 -> 1043700 | I27: =I25+I26 -> 671000 | J27: =J25+J26 -> 1025300 | K27: =K25+K26 -> 266600 | ... O27: =O25+O26 -> 1088800 | P27: =SUM(D27:O27) -> 10492800
B28: IX. ± RÉSULTAT NON COURANT | C28: CPC | D28: =CPC!D52 -> 0 | E28: =CPC!E52 -> 0 | F28: =CPC!F52 -> -20000 | G28: =CPC!G52 -> 0 | H28: =CPC!H52 -> 0 | I28: =CPC!I52 -> 0 | J28: =CPC!J52 -> 0 | K28: =CPC!K52 -> 0 | ... O28: =CPC!O52 -> 0 | P28: =SUM(D28:O28) -> 20000
B29: 15. − Impôts sur les résultats | C29: CPC | D29: =CPC!D54 -> 93700 | E29: =CPC!E54 -> 184600 | F29: =CPC!F54 -> 198600 | G29: =CPC!G54 -> 157100 | H29: =CPC!H54 -> 208700 | I29: =CPC!I54 -> 134200 | J29: =CPC!J54 -> 205100 | K29: =CPC!K54 -> 53300 | ... O29: =CPC!O54 -> 217800 | P29: =SUM(D29:O29) -> 2102600
B30: X. = RÉSULTAT NET DE L'EXERCICE (+ ou −) | D30: =D27+D28-D29 -> 374800 | E30: =E27+E28-E29 -> 738200 | F30: =F27+F28-F29 -> 794500 | G30: =G27+G28-G29 -> 628300 | H30: =H27+H28-H29 -> 835000 | I30: =I27+I28-I29 -> 536800 | J30: =J27+J28-J29 -> 820200 | K30: =K27+K28-K29 -> 213300 | ... O30: =O27+O28-O29 -> 871000 | P30: =SUM(D30:O30) -> 8410200
A31: B | B31: CAPACITÉ D'AUTOFINANCEMENT (CAF) — méthode additive CGNC
B32: 1. Résultat net de l'exercice | C32: ESG | D32: =D30 -> 374800 | E32: =E30 -> 738200 | F32: =F30 -> 794500 | G32: =G30 -> 628300 | H32: =H30 -> 835000 | I32: =I30 -> 536800 | J32: =J30 -> 820200 | K32: =K30 -> 213300 | ... O32: =O30 -> 871000 | P32: =SUM(D32:O32) -> 8410200
B33: 2. + Dotations d'exploitation (hors actif circulant) | C33: Balance | D33: =IFERROR(SUMPRODUCT((LEFT(Balance!$A$6:$A$75,3)="619")*(LEFT(Balance!$A$6:$A$75,4)<>"6196")*(LEFT(Balance!$A$6:$A$75,4)<>"6197")*Balance!F$6:F$75),0) -> 382500 | E33: =IFERROR(SUMPRODUCT((LEFT(Balance!$A$6:$A$75,3)="619")*(LEFT(Balance!$A$6:$A$75,4)<>"6196")*(LEFT(Balance!$A$6:$A$75,4)<>"6197")*Balance!G$6:G$75),0) -> 382500 | F33: =IFERROR(SUMPRODUCT((LEFT(Balance!$A$6:$A$75,3)="619")*(LEFT(Balance!$A$6:$A$75,4)<>"6196")*(LEFT(Balance!$A$6:$A$75,4)<>"6197")*Balance!H$6:H$75),0) -> 382500 | G33: =IFERROR(SUMPRODUCT((LEFT(Balance!$A$6:$A$75,3)="619")*(LEFT(Balance!$A$6:$A$75,4)<>"6196")*(LEFT(Balance!$A$6:$A$75,4)<>"6197")*Balance!I$6:I$75),0) -> 382500 | H33: =IFERROR(SUMPRODUCT((LEFT(Balance!$A$6:$A$75,3)="619")*(LEFT(Balance!$A$6:$A$75,4)<>"6196")*(LEFT(Balance!$A$6:$A$75,4)<>"6197")*Balance!J$6:J$75),0) -> 397500 | I33: =IFERROR(SUMPRODUCT((LEFT(Balance!$A$6:$A$75,3)="619")*(LEFT(Balance!$A$6:$A$75,4)<>"6196")*(LEFT(Balance!$A$6:$A$75,4)<>"6197")*Balance!K$6:K$75),0) -> 397500 | J33: =IFERROR(SUMPRODUCT((LEFT(Balance!$A$6:$A$75,3)="619")*(LEFT(Balance!$A$6:$A$75,4)<>"6196")*(LEFT(Balance!$A$6:$A$75,4)<>"6197")*Balance!L$6:L$75),0) -> 397500 | K33: =IFERROR(SUMPRODUCT((LEFT(Balance!$A$6:$A$75,3)="619")*(LEFT(Balance!$A$6:$A$75,4)<>"6196")*(LEFT(Balance!$A$6:$A$75,4)<>"6197")*Balance!M$6:M$75),0) -> 397500 | ... O33: =IFERROR(SUMPRODUCT((LEFT(Balance!$A$6:$A$75,3)="619")*(LEFT(Balance!$A$6:$A$75,4)<>"6196")*(LEFT(Balance!$A$6:$A$75,4)<>"6197")*Balance!Q$6:Q$75),0) -> 389500 | P33: =SUM(D33:O33) -> 4694000
B34: 3. + Dotations financières | C34: CPC | D34: =CPC!D35 -> 0 | E34: =CPC!E35 -> 0 | F34: =CPC!F35 -> 0 | G34: =CPC!G35 -> 0 | H34: =CPC!H35 -> 0 | I34: =CPC!I35 -> 0 | J34: =CPC!J35 -> 0 | K34: =CPC!K35 -> 0 | ... O34: =CPC!O35 -> 0 | P34: =SUM(D34:O34) -> 0
B35: 4. + Dotations non courantes | C35: CPC | D35: =CPC!D50 -> 0 | E35: =CPC!E50 -> 0 | F35: =CPC!F50 -> 0 | G35: =CPC!G50 -> 0 | H35: =CPC!H50 -> 0 | I35: =CPC!I50 -> 0 | J35: =CPC!J50 -> 0 | K35: =CPC!K50 -> 0 | ... O35: =CPC!O50 -> 0 | P35: =SUM(D35:O35) -> 0
B36: 5. − Reprises d'exploitation (hors actif circulant et transferts de charges) | C36: Balance | D36: =IFERROR(SUMPRODUCT((LEFT(Balance!$A$6:$A$75,3)="719")*(LEFT(Balance!$A$6:$A$75,4)<>"7196")*(LEFT(Balance!$A$6:$A$75,4)<>"7197")*Balance!F$6:F$75),0) -> 0 | E36: =IFERROR(SUMPRODUCT((LEFT(Balance!$A$6:$A$75,3)="719")*(LEFT(Balance!$A$6:$A$75,4)<>"7196")*(LEFT(Balance!$A$6:$A$75,4)<>"7197")*Balance!G$6:G$75),0) -> 0 | F36: =IFERROR(SUMPRODUCT((LEFT(Balance!$A$6:$A$75,3)="719")*(LEFT(Balance!$A$6:$A$75,4)<>"7196")*(LEFT(Balance!$A$6:$A$75,4)<>"7197")*Balance!H$6:H$75),0) -> 0 | G36: =IFERROR(SUMPRODUCT((LEFT(Balance!$A$6:$A$75,3)="719")*(LEFT(Balance!$A$6:$A$75,4)<>"7196")*(LEFT(Balance!$A$6:$A$75,4)<>"7197")*Balance!I$6:I$75),0) -> 0 | H36: =IFERROR(SUMPRODUCT((LEFT(Balance!$A$6:$A$75,3)="719")*(LEFT(Balance!$A$6:$A$75,4)<>"7196")*(LEFT(Balance!$A$6:$A$75,4)<>"7197")*Balance!J$6:J$75),0) -> 0 | I36: =IFERROR(SUMPRODUCT((LEFT(Balance!$A$6:$A$75,3)="719")*(LEFT(Balance!$A$6:$A$75,4)<>"7196")*(LEFT(Balance!$A$6:$A$75,4)<>"7197")*Balance!K$6:K$75),0) -> 0 | J36: =IFERROR(SUMPRODUCT((LEFT(Balance!$A$6:$A$75,3)="719")*(LEFT(Balance!$A$6:$A$75,4)<>"7196")*(LEFT(Balance!$A$6:$A$75,4)<>"7197")*Balance!L$6:L$75),0) -> 0 | K36: =IFERROR(SUMPRODUCT((LEFT(Balance!$A$6:$A$75,3)="719")*(LEFT(Balance!$A$6:$A$75,4)<>"7196")*(LEFT(Balance!$A$6:$A$75,4)<>"7197")*Balance!M$6:M$75),0) -> 0 | ... O36: =IFERROR(SUMPRODUCT((LEFT(Balance!$A$6:$A$75,3)="719")*(LEFT(Balance!$A$6:$A$75,4)<>"7196")*(LEFT(Balance!$A$6:$A$75,4)<>"7197")*Balance!Q$6:Q$75),0) -> 0 | P36: =SUM(D36:O36) -> 0
B37: 6. − Reprises financières | C37: CPC | D37: =CPC!D29 -> 0 | E37: =CPC!E29 -> 0 | F37: =CPC!F29 -> 0 | G37: =CPC!G29 -> 0 | H37: =CPC!H29 -> 0 | I37: =CPC!I29 -> 0 | J37: =CPC!J29 -> 0 | K37: =CPC!K29 -> 0 | ... O37: =CPC!O29 -> 0 | P37: =SUM(D37:O37) -> 0
B38: 7. − Reprises non courantes | C38: CPC | D38: =CPC!D44 -> 0 | E38: =CPC!E44 -> 0 | F38: =CPC!F44 -> 0 | G38: =CPC!G44 -> 0 | H38: =CPC!H44 -> 0 | I38: =CPC!I44 -> 0 | J38: =CPC!J44 -> 0 | K38: =CPC!K44 -> 0 | ... O38: =CPC!O44 -> 0 | P38: =SUM(D38:O38) -> 0
B39: 8. − Produits des cessions d'immobilisations | C39: CPC | D39: =CPC!D40 -> 0 | E39: =CPC!E40 -> 0 | F39: =CPC!F40 -> 0 | G39: =CPC!G40 -> 0 | H39: =CPC!H40 -> 0 | I39: =CPC!I40 -> 0 | J39: =CPC!J40 -> 0 | K39: =CPC!K40 -> 0 | ... O39: =CPC!O40 -> 0 | P39: =SUM(D39:O39) -> 150000
B40: 9. + Valeurs nettes d'amortissements des immobilisations cédées | C40: CPC | D40: =CPC!D47 -> 0 | E40: =CPC!E47 -> 0 | F40: =CPC!F47 -> 0 | G40: =CPC!G47 -> 0 | H40: =CPC!H47 -> 0 | I40: =CPC!I47 -> 0 | J40: =CPC!J47 -> 0 | K40: =CPC!K47 -> 0 | ... O40: =CPC!O47 -> 0 | P40: =SUM(D40:O40) -> 110000
B41: I. CAPACITÉ D'AUTOFINANCEMENT (CAF) | D41: =D32+D33+D34+D35-D36-D37-D38-D39+D40 -> 757300 | E41: =E32+E33+E34+E35-E36-E37-E38-E39+E40 -> 1120700 | F41: =F32+F33+F34+F35-F36-F37-F38-F39+F40 -> 1177000 | G41: =G32+G33+G34+G35-G36-G37-G38-G39+G40 -> 1010800 | H41: =H32+H33+H34+H35-H36-H37-H38-H39+H40 -> 1232500 | I41: =I32+I33+I34+I35-I36-I37-I38-I39+I40 -> 934300 | J41: =J32+J33+J34+J35-J36-J37-J38-J39+J40 -> 1217700 | K41: =K32+K33+K34+K35-K36-K37-K38-K39+K40 -> 610800 | ... O41: =O32+O33+O34+O35-O36-O37-O38-O39+O40 -> 1260500 | P41: =SUM(D41:O41) -> 13064200
B43: Contrôle : Résultat net ESG − Résultat net CPC (doit être 0) | D43: =D30-CPC!D55 -> 0 | E43: =E30-CPC!E55 -> 0 | F43: =F30-CPC!F55 -> 0 | G43: =G30-CPC!G55 -> 0 | H43: =H30-CPC!H55 -> 0 | I43: =I30-CPC!I55 -> 0 | J43: =J30-CPC!J55 -> 0 | K43: =K30-CPC!K55 -> 0 | ... P43: =P30-CPC!P55 -> 0

Sheet Reporting
A1: REPORTING — Indicateurs clés et élasticité CA / REX — 2023 | Q1: ⌂ Accueil
A2: Formules vivantes alimentées par le CPC, l'ESG et la Balance · Choisissez un mois en C4 · Données fictives
A4: ▸ MOIS SÉLECTIONNÉ (sélecteur) | C4: Décembre | D4: ← cliquez sur la cellule et choisissez un mois dans la liste
A5: Seuil « non significatif » : |variation du CA| inférieure à | C5: 0.02
A6: Élasticité « proportionnelle » : borne basse | C6: 0.8
A7: Élasticité « proportionnelle » : borne haute | C7: 1.2
A9: Indicateur | B9: Unité | C9: Repère | D9: Janvier | E9: Février | F9: Mars | G9: Avril | H9: Mai | I9: Juin | J9: Juillet | K9: Août | L9: Septembre | M9: Octobre | N9: Novembre | O9: Décembre | P9: Année 2023 | Q9: Mois sélectionné
A10: 1. ÉLASTICITÉ CA / REX — le résultat d'exploitation suit-il le chiffre d'affaires ?
A11: Chiffre d'affaires | B11: MAD | D11: =CPC!D8 -> 6460000 | E11: =CPC!E8 -> 6862000 | F11: =CPC!F8 -> 7530000 | G11: =CPC!G8 -> 7139000 | H11: =CPC!H8 -> 7506000 | I11: =CPC!I8 -> 7804000 | J11: =CPC!J8 -> 7378000 | K11: =CPC!K8 -> 5968000 | ... P11: =CPC!P8 -> 87975000 | Q11: =IFERROR(INDEX($D11:$O11,MATCH($C$4,$D$9:$O$9,0)),"–") -> 8220000
A12: Variation du CA vs mois précédent | B12: % | D12: – | E12: =IFERROR(E11/D11-1,"–") -> 0.062229102 | F12: =IFERROR(F11/E11-1,"–") -> 0.097347712 | G12: =IFERROR(G11/F11-1,"–") -> -0.051925631 | H12: =IFERROR(H11/G11-1,"–") -> 0.05140776 | I12: =IFERROR(I11/H11-1,"–") -> 0.039701572 | J12: =IFERROR(J11/I11-1,"–") -> -0.054587391 | K12: =IFERROR(K11/J11-1,"–") -> -0.1911087 | L12: =IFERROR(L11/K11-1,"–") -> 0.23106568 | ... O12: =IFERROR(O11/N11-1,"–") -> 0.04487098 | P12: – | Q12: =IFERROR(INDEX($D12:$O12,MATCH($C$4,$D$9:$O$9,0)),"–") -> 0.04487098
A13: Résultat d'exploitation (REX) | B13: MAD | D13: =CPC!D24 -> 547500 | E13: =CPC!E24 -> 946500 | F13: =CPC!F24 -> 1051500 | G13: =CPC!G24 -> 815500 | H13: =CPC!H24 -> 1101500 | I13: =CPC!I24 -> 758500 | J13: =CPC!J24 -> 1031500 | K13: =CPC!K24 -> 330500 | ... P13: =CPC!P24 -> 11092000 | Q13: =IFERROR(INDEX($D13:$O13,MATCH($C$4,$D$9:$O$9,0)),"–") -> 1137500
A14: Variation du REX vs mois précédent | B14: % | D14: – | E14: =IFERROR(E13/D13-1,"–") -> 0.72876712 | F14: =IFERROR(F13/E13-1,"–") -> 0.11093502 | G14: =IFERROR(G13/F13-1,"–") -> -0.22444127 | H14: =IFERROR(H13/G13-1,"–") -> 0.35070509 | I14: =IFERROR(I13/H13-1,"–") -> -0.31139355 | J14: =IFERROR(J13/I13-1,"–") -> 0.3599209 | K14: =IFERROR(K13/J13-1,"–") -> -0.67959283 | L14: =IFERROR(L13/K13-1,"–") -> 1.6369138 | ... O14: =IFERROR(O13/N13-1,"–") -> 0.02247191 | P14: – | Q14: =IFERROR(INDEX($D14:$O14,MATCH($C$4,$D$9:$O$9,0)),"–") -> 0.02247191
A15: Marge d'exploitation (REX / CA) | B15: % | C15: 10 % à 15 % | D15: =IFERROR(D13/D11,0) -> 0.084752322 | E15: =IFERROR(E13/E11,0) -> 0.13793355 | F15: =IFERROR(F13/F11,0) -> 0.13964143 | G15: =IFERROR(G13/G11,0) -> 0.11423169 | H15: =IFERROR(H13/H11,0) -> 0.14674927 | I15: =IFERROR(I13/I11,0) -> 0.097193747 | J15: =IFERROR(J13/J11,0) -> 0.13980754 | K15: =IFERROR(K13/K11,0) -> 0.055378686 | ... P15: =IFERROR(P13/P11,0) -> 0.12608127 | Q15: =IFERROR(INDEX($D15:$O15,MATCH($C$4,$D$9:$O$9,0)),"–") -> 0.138382
A16: Élasticité REX / CA | B16: coef. | C16: > 1 = levier positif | D16: – | E16: =IF(OR(E12="–",E14="–"),"–",IF(OR(ABS(E12)<$C$5,D13<=0),"n.s.",ROUND(E14/E12,1))) -> 11.7 | F16: =IF(OR(F12="–",F14="–"),"–",IF(OR(ABS(F12)<$C$5,E13<=0),"n.s.",ROUND(F14/F12,1))) -> 1.1 | G16: =IF(OR(G12="–",G14="–"),"–",IF(OR(ABS(G12)<$C$5,F13<=0),"n.s.",ROUND(G14/G12,1))) -> 4.3 | H16: =IF(OR(H12="–",H14="–"),"–",IF(OR(ABS(H12)<$C$5,G13<=0),"n.s.",ROUND(H14/H12,1))) -> 6.8 | I16: =IF(OR(I12="–",I14="–"),"–",IF(OR(ABS(I12)<$C$5,H13<=0),"n.s.",ROUND(I14/I12,1))) -> -7.8 | J16: =IF(OR(J12="–",J14="–"),"–",IF(OR(ABS(J12)<$C$5,I13<=0),"n.s.",ROUND(J14/J12,1))) -> -6.6 | K16: =IF(OR(K12="–",K14="–"),"–",IF(OR(ABS(K12)<$C$5,J13<=0),"n.s.",ROUND(K14/K12,1))) -> 3.6 | L16: =IF(OR(L12="–",L14="–"),"–",IF(OR(ABS(L12)<$C$5,K13<=0),"n.s.",ROUND(L14/L12,1))) -> 7.1 | ... O16: =IF(OR(O12="–",O14="–"),"–",IF(OR(ABS(O12)<$C$5,N13<=0),"n.s.",ROUND(O14/O12,1))) -> 0.5 | P16: – | Q16: =IFERROR(INDEX($D16:$O16,MATCH($C$4,$D$9:$O$9,0)),"–") -> 0.5
A17: Lecture de l'élasticité | C17: voir code couleur | D17: – | E17: =IF(E16="–","–",IF(E16="n.s.","n.s.",IF(E12>0,IF(E16>$C$7,"▲ Levier fort",IF(E16>=$C$6,"▲ Proportionnel",IF(E16>0,"▲ Marge érodée","▲ Sens contraire"))),IF(E16>$C$7,"▼ REX chute plus vite",IF(E16>=$C$6,"▼ Proportionnel",IF(E16>0,"▼ REX résiste","▼ REX progresse")))))) -> ▲ Levier fort | F17: =IF(F16="–","–",IF(F16="n.s.","n.s.",IF(F12>0,IF(F16>$C$7,"▲ Levier fort",IF(F16>=$C$6,"▲ Proportionnel",IF(F16>0,"▲ Marge érodée","▲ Sens contraire"))),IF(F16>$C$7,"▼ REX chute plus vite",IF(F16>=$C$6,"▼ Proportionnel",IF(F16>0,"▼ REX résiste","▼ REX progresse")))))) -> ▲ Proportionnel | G17: =IF(G16="–","–",IF(G16="n.s.","n.s.",IF(G12>0,IF(G16>$C$7,"▲ Levier fort",IF(G16>=$C$6,"▲ Proportionnel",IF(G16>0,"▲ Marge érodée","▲ Sens contraire"))),IF(G16>$C$7,"▼ REX chute plus vite",IF(G16>=$C$6,"▼ Proportionnel",IF(G16>0,"▼ REX résiste","▼ REX progresse")))))) -> ▼ REX chute plus vite | H17: =IF(H16="–","–",IF(H16="n.s.","n.s.",IF(H12>0,IF(H16>$C$7,"▲ Levier fort",IF(H16>=$C$6,"▲ Proportionnel",IF(H16>0,"▲ Marge érodée","▲ Sens contraire"))),IF(H16>$C$7,"▼ REX chute plus vite",IF(H16>=$C$6,"▼ Proportionnel",IF(H16>0,"▼ REX résiste","▼ REX progresse")))))) -> ▲ Levier fort | I17: =IF(I16="–","–",IF(I16="n.s.","n.s.",IF(I12>0,IF(I16>$C$7,"▲ Levier fort",IF(I16>=$C$6,"▲ Proportionnel",IF(I16>0,"▲ Marge érodée","▲ Sens contraire"))),IF(I16>$C$7,"▼ REX chute plus vite",IF(I16>=$C$6,"▼ Proportionnel",IF(I16>0,"▼ REX résiste","▼ REX progresse")))))) -> ▲ Sens contraire | J17: =IF(J16="–","–",IF(J16="n.s.","n.s.",IF(J12>0,IF(J16>$C$7,"▲ Levier fort",IF(J16>=$C$6,"▲ Proportionnel",IF(J16>0,"▲ Marge érodée","▲ Sens contraire"))),IF(J16>$C$7,"▼ REX chute plus vite",IF(J16>=$C$6,"▼ Proportionnel",IF(J16>0,"▼ REX résiste","▼ REX progresse")))))) -> ▼ REX progresse | K17: =IF(K16="–","–",IF(K16="n.s.","n.s.",IF(K12>0,IF(K16>$C$7,"▲ Levier fort",IF(K16>=$C$6,"▲ Proportionnel",IF(K16>0,"▲ Marge érodée","▲ Sens contraire"))),IF(K16>$C$7,"▼ REX chute plus vite",IF(K16>=$C$6,"▼ Proportionnel",IF(K16>0,"▼ REX résiste","▼ REX progresse")))))) -> ▼ REX chute plus vite | L17: =IF(L16="–","–",IF(L16="n.s.","n.s.",IF(L12>0,IF(L16>$C$7,"▲ Levier fort",IF(L16>=$C$6,"▲ Proportionnel",IF(L16>0,"▲ Marge érodée","▲ Sens contraire"))),IF(L16>$C$7,"▼ REX chute plus vite",IF(L16>=$C$6,"▼ Proportionnel",IF(L16>0,"▼ REX résiste","▼ REX progresse")))))) -> ▲ Levier fort | ... O17: =IF(O16="–","–",IF(O16="n.s.","n.s.",IF(O12>0,IF(O16>$C$7,"▲ Levier fort",IF(O16>=$C$6,"▲ Proportionnel",IF(O16>0,"▲ Marge érodée","▲ Sens contraire"))),IF(O16>$C$7,"▼ REX chute plus vite",IF(O16>=$C$6,"▼ Proportionnel",IF(O16>0,"▼ REX résiste","▼ REX progresse")))))) -> ▲ Marge érodée | P17: – | Q17: =IFERROR(INDEX($D17:$O17,MATCH($C$4,$D$9:$O$9,0)),"–") -> ▲ Marge érodée
A18: 2. RENTABILITÉ ET PERFORMANCE
A19: Poids de la masse salariale / CA | B19: % | C19: < 30 % | D19: =IFERROR(CPC!D20/D11,0) -> 0.28931889 | E19: =IFERROR(CPC!E20/E11,0) -> 0.27338968 | F19: =IFERROR(CPC!F20/F11,0) -> 0.2501992 | G19: =IFERROR(CPC!G20/G11,0) -> 0.26488304 | H19: =IFERROR(CPC!H20/H11,0) -> 0.25286438 | I19: =IFERROR(CPC!I20/I11,0) -> 0.24423373 | J19: =IFERROR(CPC!J20/J11,0) -> 0.25928436 | K19: =IFERROR(CPC!K20/K11,0) -> 0.32188338 | ... P19: =IFERROR(CPC!P20/P11,0) -> 0.26211992 | Q19: =IFERROR(INDEX($D19:$O19,MATCH($C$4,$D$9:$O$9,0)),"–") -> 0.25486618
A20: CAF / CA | B20: % | C20: > 10 % | D20: =IFERROR(ESG!D41/D11,0) -> 0.1172291 | E20: =IFERROR(ESG!E41/E11,0) -> 0.16331973 | F20: =IFERROR(ESG!F41/F11,0) -> 0.1563081 | G20: =IFERROR(ESG!G41/G11,0) -> 0.14158846 | H20: =IFERROR(ESG!H41/H11,0) -> 0.16420197 | I20: =IFERROR(ESG!I41/I11,0) -> 0.11972066 | J20: =IFERROR(ESG!J41/J11,0) -> 0.16504473 | K20: =IFERROR(ESG!K41/K11,0) -> 0.10234584 | ... P20: =IFERROR(ESG!P41/P11,0) -> 0.14849901 | Q20: =IFERROR(INDEX($D20:$O20,MATCH($C$4,$D$9:$O$9,0)),"–") -> 0.1533455
A21: Résultat net | B21: MAD | D21: =CPC!D55 -> 374800 | E21: =CPC!E55 -> 738200 | F21: =CPC!F55 -> 794500 | G21: =CPC!G55 -> 628300 | H21: =CPC!H55 -> 835000 | I21: =CPC!I55 -> 536800 | J21: =CPC!J55 -> 820200 | K21: =CPC!K55 -> 213300 | ... P21: =CPC!P55 -> 8410200 | Q21: =IFERROR(INDEX($D21:$O21,MATCH($C$4,$D$9:$O$9,0)),"–") -> 871000
A22: Résultat net N-1 (même mois 2022) | B22: MAD | D22: =Balance!F81 -> 345400 | E22: =Balance!G81 -> 689100 | F22: =Balance!H81 -> 731500 | G22: =Balance!I81 -> 579200 | H22: =Balance!J81 -> 791900 | I22: =Balance!K81 -> 494100 | J22: =Balance!L81 -> 757600 | K22: =Balance!M81 -> 195300 | ... P22: =Balance!R81 -> 7823000 | Q22: =IFERROR(INDEX($D22:$O22,MATCH($C$4,$D$9:$O$9,0)),"–") -> 795800
A23: Taux de croissance du résultat net (vs N-1) | B23: % | C23: 5 % à 10 % | D23: =IFERROR(D21/D22-1,"–") -> 0.085118703 | E23: =IFERROR(E21/E22-1,"–") -> 0.071252358 | F23: =IFERROR(F21/F22-1,"–") -> 0.086124402 | G23: =IFERROR(G21/G22-1,"–") -> 0.084772099 | H23: =IFERROR(H21/H22-1,"–") -> 0.054426064 | I23: =IFERROR(I21/I22-1,"–") -> 0.086419753 | J23: =IFERROR(J21/J22-1,"–") -> 0.082629356 | K23: =IFERROR(K21/K22-1,"–") -> 0.092165899 | ... P23: =IFERROR(P21/P22-1,"–") -> 0.075060718 | Q23: =IFERROR(INDEX($D23:$O23,MATCH($C$4,$D$9:$O$9,0)),"–") -> 0.094496105
A24: Ratio de densité des charges externes (charges externes / CA) | B24: % | C24: < 10 % | D24: =IFERROR(CPC!D18/D11,0) -> 0.065325077 | E24: =IFERROR(CPC!E18/E11,0) -> 0.064412708 | F24: =IFERROR(CPC!F18/F11,0) -> 0.060823373 | G24: =IFERROR(CPC!G18/G11,0) -> 0.062193585 | H24: =IFERROR(CPC!H18/H11,0) -> 0.073541167 | I24: =IFERROR(CPC!I18/I11,0) -> 0.11391594 | J24: =IFERROR(CPC!J18/J11,0) -> 0.061669829 | K24: =IFERROR(CPC!K18/K11,0) -> 0.068364611 | ... P24: =IFERROR(CPC!P18/P11,0) -> 0.067587383 | Q24: =IFERROR(INDEX($D24:$O24,MATCH($C$4,$D$9:$O$9,0)),"–") -> 0.05863747
A25: Charges variables (matières, sous-traitance, énergie, transports) | B25: MAD | C25: hypothèse | D25: =IFERROR(SUMPRODUCT((LEFT(Balance!$A$6:$A$75,4)="6121")*Balance!F$6:F$75)+SUMPRODUCT((LEFT(Balance!$A$6:$A$75,4)="6122")*Balance!F$6:F$75)+SUMPRODUCT((LEFT(Balance!$A$6:$A$75,4)="6124")*Balance!F$6:F$75)+SUMPRODUCT((LEFT(Balance!$A$6:$A$75,4)="6125")*Balance!F$6:F$75)+SUMPRODUCT((LEFT(Balance!$A$6:$A$75,4)="6126")*Balance!F$6:F$75)+SUMPRODUCT((LEFT(Balance!$A$6:$A$75,4)="6142")*Balance!F$6:F$75),0) -> 3202000 | E25: =IFERROR(SUMPRODUCT((LEFT(Balance!$A$6:$A$75,4)="6121")*Balance!G$6:G$75)+SUMPRODUCT((LEFT(Balance!$A$6:$A$75,4)="6122")*Balance!G$6:G$75)+SUMPRODUCT((LEFT(Balance!$A$6:$A$75,4)="6124")*Balance!G$6:G$75)+SUMPRODUCT((LEFT(Balance!$A$6:$A$75,4)="6125")*Balance!G$6:G$75)+SUMPRODUCT((LEFT(Balance!$A$6:$A$75,4)="6126")*Balance!G$6:G$75)+SUMPRODUCT((LEFT(Balance!$A$6:$A$75,4)="6142")*Balance!G$6:G$75),0) -> 3626000 | F25: =IFERROR(SUMPRODUCT((LEFT(Balance!$A$6:$A$75,4)="6121")*Balance!H$6:H$75)+SUMPRODUCT((LEFT(Balance!$A$6:$A$75,4)="6122")*Balance!H$6:H$75)+SUMPRODUCT((LEFT(Balance!$A$6:$A$75,4)="6124")*Balance!H$6:H$75)+SUMPRODUCT((LEFT(Balance!$A$6:$A$75,4)="6125")*Balance!H$6:H$75)+SUMPRODUCT((LEFT(Balance!$A$6:$A$75,4)="6126")*Balance!H$6:H$75)+SUMPRODUCT((LEFT(Balance!$A$6:$A$75,4)="6142")*Balance!H$6:H$75),0) -> 3761000 | G25: =IFERROR(SUMPRODUCT((LEFT(Balance!$A$6:$A$75,4)="6121")*Balance!I$6:I$75)+SUMPRODUCT((LEFT(Balance!$A$6:$A$75,4)="6122")*Balance!I$6:I$75)+SUMPRODUCT((LEFT(Balance!$A$6:$A$75,4)="6124")*Balance!I$6:I$75)+SUMPRODUCT((LEFT(Balance!$A$6:$A$75,4)="6125")*Balance!I$6:I$75)+SUMPRODUCT((LEFT(Balance!$A$6:$A$75,4)="6126")*Balance!I$6:I$75)+SUMPRODUCT((LEFT(Balance!$A$6:$A$75,4)="6142")*Balance!I$6:I$75),0) -> 3517000 | H25: =IFERROR(SUMPRODUCT((LEFT(Balance!$A$6:$A$75,4)="6121")*Balance!J$6:J$75)+SUMPRODUCT((LEFT(Balance!$A$6:$A$75,4)="6122")*Balance!J$6:J$75)+SUMPRODUCT((LEFT(Balance!$A$6:$A$75,4)="6124")*Balance!J$6:J$75)+SUMPRODUCT((LEFT(Balance!$A$6:$A$75,4)="6125")*Balance!J$6:J$75)+SUMPRODUCT((LEFT(Balance!$A$6:$A$75,4)="6126")*Balance!J$6:J$75)+SUMPRODUCT((LEFT(Balance!$A$6:$A$75,4)="6142")*Balance!J$6:J$75),0) -> 3929000 | I25: =IFERROR(SUMPRODUCT((LEFT(Balance!$A$6:$A$75,4)="6121")*Balance!K$6:K$75)+SUMPRODUCT((LEFT(Balance!$A$6:$A$75,4)="6122")*Balance!K$6:K$75)+SUMPRODUCT((LEFT(Balance!$A$6:$A$75,4)="6124")*Balance!K$6:K$75)+SUMPRODUCT((LEFT(Balance!$A$6:$A$75,4)="6125")*Balance!K$6:K$75)+SUMPRODUCT((LEFT(Balance!$A$6:$A$75,4)="6126")*Balance!K$6:K$75)+SUMPRODUCT((LEFT(Balance!$A$6:$A$75,4)="6142")*Balance!K$6:K$75),0) -> 3995000 | J25: =IFERROR(SUMPRODUCT((LEFT(Balance!$A$6:$A$75,4)="6121")*Balance!L$6:L$75)+SUMPRODUCT((LEFT(Balance!$A$6:$A$75,4)="6122")*Balance!L$6:L$75)+SUMPRODUCT((LEFT(Balance!$A$6:$A$75,4)="6124")*Balance!L$6:L$75)+SUMPRODUCT((LEFT(Balance!$A$6:$A$75,4)="6125")*Balance!L$6:L$75)+SUMPRODUCT((LEFT(Balance!$A$6:$A$75,4)="6126")*Balance!L$6:L$75)+SUMPRODUCT((LEFT(Balance!$A$6:$A$75,4)="6142")*Balance!L$6:L$75),0) -> 3779000 | K25: =IFERROR(SUMPRODUCT((LEFT(Balance!$A$6:$A$75,4)="6121")*Balance!M$6:M$75)+SUMPRODUCT((LEFT(Balance!$A$6:$A$75,4)="6122")*Balance!M$6:M$75)+SUMPRODUCT((LEFT(Balance!$A$6:$A$75,4)="6124")*Balance!M$6:M$75)+SUMPRODUCT((LEFT(Balance!$A$6:$A$75,4)="6125")*Balance!M$6:M$75)+SUMPRODUCT((LEFT(Balance!$A$6:$A$75,4)="6126")*Balance!M$6:M$75)+SUMPRODUCT((LEFT(Balance!$A$6:$A$75,4)="6142")*Balance!M$6:M$75),0) -> 3034000 | ... O25: =IFERROR(SUMPRODUCT((LEFT(Balance!$A$6:$A$75,4)="6121")*Balance!Q$6:Q$75)+SUMPRODUCT((LEFT(Balance!$A$6:$A$75,4)="6122")*Balance!Q$6:Q$75)+SUMPRODUCT((LEFT(Balance!$A$6:$A$75,4)="6124")*Balance!Q$6:Q$75)+SUMPRODUCT((LEFT(Balance!$A$6:$A$75,4)="6125")*Balance!Q$6:Q$75)+SUMPRODUCT((LEFT(Balance!$A$6:$A$75,4)="6126")*Balance!Q$6:Q$75)+SUMPRODUCT((LEFT(Balance!$A$6:$A$75,4)="6142")*Balance!Q$6:Q$75),0) -> 4169000 | P25: =SUM(D25:O25) -> 44721000 | Q25: =IFERROR(INDEX($D25:$O25,MATCH($C$4,$D$9:$O$9,0)),"–") -> 4169000
A26: Marge sur coûts variables (MCV) | B26: MAD | D26: =ESG!D12+CPC!D6-CPC!D16-D25 -> 3065000 | E26: =ESG!E12+CPC!E6-CPC!E16-E25 -> 3483000 | F26: =ESG!F12+CPC!F6-CPC!F16-F25 -> 3600000 | G26: =ESG!G12+CPC!G6-CPC!G16-G25 -> 3364000 | H26: =ESG!H12+CPC!H6-CPC!H16-H25 -> 3774000 | I26: =ESG!I12+CPC!I6-CPC!I16-I25 -> 3831000 | J26: =ESG!J12+CPC!J6-CPC!J16-J25 -> 3624000 | K26: =ESG!K12+CPC!K6-CPC!K16-K25 -> 2910000 | ... O26: =ESG!O12+CPC!O6-CPC!O16-O25 -> 3996000 | P26: =SUM(D26:O26) -> 42868000 | Q26: =IFERROR(INDEX($D26:$O26,MATCH($C$4,$D$9:$O$9,0)),"–") -> 3996000
A27: Effet de levier opérationnel (MCV / REX) | B27: x | C27: 2x à 4x | D27: =IF(D13<=0,"n.s.",IFERROR(D26/D13,"n.s.")) -> 5.5981735 | E27: =IF(E13<=0,"n.s.",IFERROR(E26/E13,"n.s.")) -> 3.6798732 | F27: =IF(F13<=0,"n.s.",IFERROR(F26/F13,"n.s.")) -> 3.4236805 | G27: =IF(G13<=0,"n.s.",IFERROR(G26/G13,"n.s.")) -> 4.1250766 | H27: =IF(H13<=0,"n.s.",IFERROR(H26/H13,"n.s.")) -> 3.4262369 | I27: =IF(I13<=0,"n.s.",IFERROR(I26/I13,"n.s.")) -> 5.0507581 | J27: =IF(J13<=0,"n.s.",IFERROR(J26/J13,"n.s.")) -> 3.5133301 | K27: =IF(K13<=0,"n.s.",IFERROR(K26/K13,"n.s.")) -> 8.8048411 | ... P27: =IF(P13<=0,"n.s.",IFERROR(P26/P13,"n.s.")) -> 3.8647674 | Q27: =IFERROR(INDEX($D27:$O27,MATCH($C$4,$D$9:$O$9,0)),"–") -> 3.512967
A28: 3. INDICATEURS SPÉCIFIQUES AÉRONAUTIQUE
A29: Production de l'exercice | B29: MAD | D29: =ESG!D12 -> 6234000 | E29: =ESG!E12 -> 7074000 | F29: =ESG!F12 -> 7323000 | G29: =ESG!G12 -> 6845000 | H29: =ESG!H12 -> 7665000 | I29: =ESG!I12 -> 7786000 | J29: =ESG!J12 -> 7365000 | K29: =ESG!K12 -> 5914000 | ... O29: =ESG!O12 -> 8123000 | P29: =SUM(D29:O29) -> 87142000 | Q29: =IFERROR(INDEX($D29:$O29,MATCH($C$4,$D$9:$O$9,0)),"–") -> 8123000
A30: Valeur ajoutée | B30: MAD | D30: =ESG!D16 -> 2759000 | E30: =ESG!E16 -> 3165000 | F30: =ESG!F16 -> 3278000 | G30: =ESG!G16 -> 3049000 | H30: =ESG!H16 -> 3357000 | I30: =ESG!I16 -> 3082000 | J30: =ESG!J16 -> 3302000 | K30: =ESG!K16 -> 2609000 | ... O30: =ESG!O16 -> 3662000 | P30: =SUM(D30:O30) -> 38506000 | Q30: =IFERROR(INDEX($D30:$O30,MATCH($C$4,$D$9:$O$9,0)),"–") -> 3662000
A31: Taux de valeur ajoutée locale (VA / Production) | B31: % | C31: > 40 % | D31: =IFERROR(D30/D29,0) -> 0.44257299 | E31: =IFERROR(E30/E29,0) -> 0.44741306 | F31: =IFERROR(F30/F29,0) -> 0.44763075 | G31: =IFERROR(G30/G29,0) -> 0.44543462 | H31: =IFERROR(H30/H29,0) -> 0.43796477 | I31: =IFERROR(I30/I29,0) -> 0.39583868 | J31: =IFERROR(J30/J29,0) -> 0.44833673 | K31: =IFERROR(K30/K29,0) -> 0.44115658 | ... P31: =IFERROR(P30/P29,0) -> 0.44187648 | Q31: =IFERROR(INDEX($D31:$O31,MATCH($C$4,$D$9:$O$9,0)),"–") -> 0.45081866
A32: Poids du personnel dans la valeur ajoutée | B32: % | C32: < 65 % sain | D32: =IFERROR(CPC!D20/D30,0) -> 0.67741935 | E32: =IFERROR(CPC!E20/E30,0) -> 0.59273302 | F32: =IFERROR(CPC!F20/F30,0) -> 0.5747407 | G32: =IFERROR(CPC!G20/G30,0) -> 0.62020335 | H32: =IFERROR(CPC!H20/H30,0) -> 0.56538576 | I32: =IFERROR(CPC!I20/I30,0) -> 0.61842959 | J32: =IFERROR(CPC!J20/J30,0) -> 0.57934585 | K32: =IFERROR(CPC!K20/K30,0) -> 0.73629743 | ... P32: =IFERROR(CPC!P20/P30,0) -> 0.59886771 | Q32: =IFERROR(INDEX($D32:$O32,MATCH($C$4,$D$9:$O$9,0)),"–") -> 0.57209175
A33: Résultat de change net (gains − pertes) | B33: MAD | D33: =CPC!D27-CPC!D33 -> 20000 | E33: =CPC!E27-CPC!E33 -> 74000 | F33: =CPC!F27-CPC!F33 -> 58000 | G33: =CPC!G27-CPC!G33 -> 65000 | H33: =CPC!H27-CPC!H33 -> 36000 | I33: =CPC!I27-CPC!I33 -> 5000 | J33: =CPC!J27-CPC!J33 -> 85000 | K33: =CPC!K27-CPC!K33 -> 26000 | ... O33: =CPC!O27-CPC!O33 -> 36000 | P33: =SUM(D33:O33) -> 503000 | Q33: =IFERROR(INDEX($D33:$O33,MATCH($C$4,$D$9:$O$9,0)),"–") -> 36000
A34: REX corrigé du change | B34: MAD | D34: =D13+D33 -> 567500 | E34: =E13+E33 -> 1020500 | F34: =F13+F33 -> 1109500 | G34: =G13+G33 -> 880500 | H34: =H13+H33 -> 1137500 | I34: =I13+I33 -> 763500 | J34: =J13+J33 -> 1116500 | K34: =K13+K33 -> 356500 | ... O34: =O13+O33 -> 1173500 | P34: =SUM(D34:O34) -> 11595000 | Q34: =IFERROR(INDEX($D34:$O34,MATCH($C$4,$D$9:$O$9,0)),"–") -> 1173500
A35: Part du change dans le REX | B35: % | C35: < 20 % | D35: =IF(D13<=0,"n.s.",IFERROR(D33/D13,"n.s.")) -> 0.03652968 | E35: =IF(E13<=0,"n.s.",IFERROR(E33/E13,"n.s.")) -> 0.078182779 | F35: =IF(F13<=0,"n.s.",IFERROR(F33/F13,"n.s.")) -> 0.055159296 | G35: =IF(G13<=0,"n.s.",IFERROR(G33/G13,"n.s.")) -> 0.079705702 | H35: =IF(H13<=0,"n.s.",IFERROR(H33/H13,"n.s.")) -> 0.032682705 | I35: =IF(I13<=0,"n.s.",IFERROR(I33/I13,"n.s.")) -> 0.0065919578 | J35: =IF(J13<=0,"n.s.",IFERROR(J33/J13,"n.s.")) -> 0.082404266 | K35: =IF(K13<=0,"n.s.",IFERROR(K33/K13,"n.s.")) -> 0.078668684 | ... P35: =IF(P13<=0,"n.s.",IFERROR(P33/P13,"n.s.")) -> 0.045347999 | Q35: =IFERROR(INDEX($D35:$O35,MATCH($C$4,$D$9:$O$9,0)),"–") -> 0.031648352
A36: 4. FINANCEMENT, BFR ET CYCLE DE TRÉSORERIE
A37: Encours de la dette bancaire (fin de mois) | B37: MAD | D37: =SUMPRODUCT((LEFT(Balance!$A$6:$A$75,3)="148")*Balance!F$6:F$75) -> 23700000 | E37: =SUMPRODUCT((LEFT(Balance!$A$6:$A$75,3)="148")*Balance!G$6:G$75) -> 23400000 | F37: =SUMPRODUCT((LEFT(Balance!$A$6:$A$75,3)="148")*Balance!H$6:H$75) -> 23100000 | G37: =SUMPRODUCT((LEFT(Balance!$A$6:$A$75,3)="148")*Balance!I$6:I$75) -> 22800000 | H37: =SUMPRODUCT((LEFT(Balance!$A$6:$A$75,3)="148")*Balance!J$6:J$75) -> 22500000 | I37: =SUMPRODUCT((LEFT(Balance!$A$6:$A$75,3)="148")*Balance!K$6:K$75) -> 22200000 | J37: =SUMPRODUCT((LEFT(Balance!$A$6:$A$75,3)="148")*Balance!L$6:L$75) -> 21900000 | K37: =SUMPRODUCT((LEFT(Balance!$A$6:$A$75,3)="148")*Balance!M$6:M$75) -> 21600000 | ... O37: =SUMPRODUCT((LEFT(Balance!$A$6:$A$75,3)="148")*Balance!Q$6:Q$75) -> 20400000 | P37: =O37 -> 20400000 | Q37: =IFERROR(INDEX($D37:$O37,MATCH($C$4,$D$9:$O$9,0)),"–") -> 20400000
A38: Charges d'intérêts | B38: MAD | D38: =CPC!D32 -> 104000 | E38: =CPC!E32 -> 102700 | F38: =CPC!F32 -> 101400 | G38: =CPC!G32 -> 100100 | H38: =CPC!H32 -> 98800 | I38: =CPC!I32 -> 97500 | J38: =CPC!J32 -> 96200 | K38: =CPC!K32 -> 94900 | ... O38: =CPC!O32 -> 89700 | P38: =SUM(D38:O38) -> 1162200 | Q38: =IFERROR(INDEX($D38:$O38,MATCH($C$4,$D$9:$O$9,0)),"–") -> 89700
A39: Coût moyen de la dette (annualisé) | B39: % | C39: 4 % à 7 % | D39: =IFERROR(D38*12/D37,0) -> 0.052658228 | E39: =IFERROR(E38*12/E37,0) -> 0.052666667 | F39: =IFERROR(F38*12/F37,0) -> 0.052675325 | G39: =IFERROR(G38*12/G37,0) -> 0.052684211 | H39: =IFERROR(H38*12/H37,0) -> 0.052693333 | I39: =IFERROR(I38*12/I37,0) -> 0.052702703 | J39: =IFERROR(J38*12/J37,0) -> 0.052712329 | K39: =IFERROR(K38*12/K37,0) -> 0.052722222 | ... O39: =IFERROR(O38*12/O37,0) -> 0.052764706 | P39: =IFERROR(P38/AVERAGE(D37:O37),0) -> 0.052707483 | Q39: =IFERROR(INDEX($D39:$O39,MATCH($C$4,$D$9:$O$9,0)),"–") -> 0.052764706
A40: Stocks (matières, en-cours, produits finis) | B40: MAD | D40: =SUMPRODUCT((LEFT(Balance!$A$6:$A$75,2)="31")*Balance!F$6:F$75) -> 16392000 | E40: =SUMPRODUCT((LEFT(Balance!$A$6:$A$75,2)="31")*Balance!G$6:G$75) -> 16614000 | F40: =SUMPRODUCT((LEFT(Balance!$A$6:$A$75,2)="31")*Balance!H$6:H$75) -> 16628000 | G40: =SUMPRODUCT((LEFT(Balance!$A$6:$A$75,2)="31")*Balance!I$6:I$75) -> 16430000 | H40: =SUMPRODUCT((LEFT(Balance!$A$6:$A$75,2)="31")*Balance!J$6:J$75) -> 16898000 | I40: =SUMPRODUCT((LEFT(Balance!$A$6:$A$75,2)="31")*Balance!K$6:K$75) -> 17023000 | J40: =SUMPRODUCT((LEFT(Balance!$A$6:$A$75,2)="31")*Balance!L$6:L$75) -> 17131000 | K40: =SUMPRODUCT((LEFT(Balance!$A$6:$A$75,2)="31")*Balance!M$6:M$75) -> 17149000 | ... O40: =SUMPRODUCT((LEFT(Balance!$A$6:$A$75,2)="31")*Balance!Q$6:Q$75) -> 17363000 | P40: =O40 -> 17363000 | Q40: =IFERROR(INDEX($D40:$O40,MATCH($C$4,$D$9:$O$9,0)),"–") -> 17363000
A41: Créances clients (brut) | B41: MAD | D41: =SUMPRODUCT((LEFT(Balance!$A$6:$A$75,3)="342")*Balance!F$6:F$75) -> 13008000 | E41: =SUMPRODUCT((LEFT(Balance!$A$6:$A$75,3)="342")*Balance!G$6:G$75) -> 14800000 | F41: =SUMPRODUCT((LEFT(Balance!$A$6:$A$75,3)="342")*Balance!H$6:H$75) -> 15364000 | G41: =SUMPRODUCT((LEFT(Balance!$A$6:$A$75,3)="342")*Balance!I$6:I$75) -> 15216000 | H41: =SUMPRODUCT((LEFT(Balance!$A$6:$A$75,3)="342")*Balance!J$6:J$75) -> 14074000 | I41: =SUMPRODUCT((LEFT(Balance!$A$6:$A$75,3)="342")*Balance!K$6:K$75) -> 16587000 | J41: =SUMPRODUCT((LEFT(Balance!$A$6:$A$75,3)="342")*Balance!L$6:L$75) -> 15072000 | K41: =SUMPRODUCT((LEFT(Balance!$A$6:$A$75,3)="342")*Balance!M$6:M$75) -> 11500000 | ... O41: =SUMPRODUCT((LEFT(Balance!$A$6:$A$75,3)="342")*Balance!Q$6:Q$75) -> 15516000 | P41: =O41 -> 15516000 | Q41: =IFERROR(INDEX($D41:$O41,MATCH($C$4,$D$9:$O$9,0)),"–") -> 15516000
A42: − Provisions pour dépréciation des clients | B42: MAD | D42: =SUMPRODUCT((LEFT(Balance!$A$6:$A$75,3)="394")*Balance!F$6:F$75) -> 180000 | E42: =SUMPRODUCT((LEFT(Balance!$A$6:$A$75,3)="394")*Balance!G$6:G$75) -> 180000 | F42: =SUMPRODUCT((LEFT(Balance!$A$6:$A$75,3)="394")*Balance!H$6:H$75) -> 180000 | G42: =SUMPRODUCT((LEFT(Balance!$A$6:$A$75,3)="394")*Balance!I$6:I$75) -> 180000 | H42: =SUMPRODUCT((LEFT(Balance!$A$6:$A$75,3)="394")*Balance!J$6:J$75) -> 180000 | I42: =SUMPRODUCT((LEFT(Balance!$A$6:$A$75,3)="394")*Balance!K$6:K$75) -> 240000 | J42: =SUMPRODUCT((LEFT(Balance!$A$6:$A$75,3)="394")*Balance!L$6:L$75) -> 240000 | K42: =SUMPRODUCT((LEFT(Balance!$A$6:$A$75,3)="394")*Balance!M$6:M$75) -> 240000 | ... O42: =SUMPRODUCT((LEFT(Balance!$A$6:$A$75,3)="394")*Balance!Q$6:Q$75) -> 285000 | P42: =O42 -> 285000 | Q42: =IFERROR(INDEX($D42:$O42,MATCH($C$4,$D$9:$O$9,0)),"–") -> 285000
A43: Autres créances d'exploitation (État) | B43: MAD | D43: =SUMPRODUCT((LEFT(Balance!$A$6:$A$75,3)="345")*Balance!F$6:F$75) -> 252000 | E43: =SUMPRODUCT((LEFT(Balance!$A$6:$A$75,3)="345")*Balance!G$6:G$75) -> 274000 | F43: =SUMPRODUCT((LEFT(Balance!$A$6:$A$75,3)="345")*Balance!H$6:H$75) -> 307000 | G43: =SUMPRODUCT((LEFT(Balance!$A$6:$A$75,3)="345")*Balance!I$6:I$75) -> 272000 | H43: =SUMPRODUCT((LEFT(Balance!$A$6:$A$75,3)="345")*Balance!J$6:J$75) -> 323000 | I43: =SUMPRODUCT((LEFT(Balance!$A$6:$A$75,3)="345")*Balance!K$6:K$75) -> 339000 | J43: =SUMPRODUCT((LEFT(Balance!$A$6:$A$75,3)="345")*Balance!L$6:L$75) -> 293000 | K43: =SUMPRODUCT((LEFT(Balance!$A$6:$A$75,3)="345")*Balance!M$6:M$75) -> 236000 | ... O43: =SUMPRODUCT((LEFT(Balance!$A$6:$A$75,3)="345")*Balance!Q$6:Q$75) -> 337000 | P43: =O43 -> 337000 | Q43: =IFERROR(INDEX($D43:$O43,MATCH($C$4,$D$9:$O$9,0)),"–") -> 337000
A44: Dettes fournisseurs | B44: MAD | D44: =SUMPRODUCT((LEFT(Balance!$A$6:$A$75,3)="441")*Balance!F$6:F$75) -> 7571000 | E44: =SUMPRODUCT((LEFT(Balance!$A$6:$A$75,3)="441")*Balance!G$6:G$75) -> 8119000 | F44: =SUMPRODUCT((LEFT(Balance!$A$6:$A$75,3)="441")*Balance!H$6:H$75) -> 9137000 | G44: =SUMPRODUCT((LEFT(Balance!$A$6:$A$75,3)="441")*Balance!I$6:I$75) -> 8719000 | H44: =SUMPRODUCT((LEFT(Balance!$A$6:$A$75,3)="441")*Balance!J$6:J$75) -> 9313000 | I44: =SUMPRODUCT((LEFT(Balance!$A$6:$A$75,3)="441")*Balance!K$6:K$75) -> 9788000 | J44: =SUMPRODUCT((LEFT(Balance!$A$6:$A$75,3)="441")*Balance!L$6:L$75) -> 9884000 | K44: =SUMPRODUCT((LEFT(Balance!$A$6:$A$75,3)="441")*Balance!M$6:M$75) -> 7297000 | ... O44: =SUMPRODUCT((LEFT(Balance!$A$6:$A$75,3)="441")*Balance!Q$6:Q$75) -> 10985000 | P44: =O44 -> 10985000 | Q44: =IFERROR(INDEX($D44:$O44,MATCH($C$4,$D$9:$O$9,0)),"–") -> 10985000
A45: Autres dettes d'exploitation (personnel, CNSS, État) | B45: MAD | D45: =SUMPRODUCT((LEFT(Balance!$A$6:$A$75,3)="443")*Balance!F$6:F$75)+SUMPRODUCT((LEFT(Balance!$A$6:$A$75,3)="444")*Balance!F$6:F$75)+SUMPRODUCT((LEFT(Balance!$A$6:$A$75,3)="445")*Balance!F$6:F$75) -> 809700 | E45: =SUMPRODUCT((LEFT(Balance!$A$6:$A$75,3)="443")*Balance!G$6:G$75)+SUMPRODUCT((LEFT(Balance!$A$6:$A$75,3)="444")*Balance!G$6:G$75)+SUMPRODUCT((LEFT(Balance!$A$6:$A$75,3)="445")*Balance!G$6:G$75) -> 1010300 | F45: =SUMPRODUCT((LEFT(Balance!$A$6:$A$75,3)="443")*Balance!H$6:H$75)+SUMPRODUCT((LEFT(Balance!$A$6:$A$75,3)="444")*Balance!H$6:H$75)+SUMPRODUCT((LEFT(Balance!$A$6:$A$75,3)="445")*Balance!H$6:H$75) -> 757000 | G45: =SUMPRODUCT((LEFT(Balance!$A$6:$A$75,3)="443")*Balance!I$6:I$75)+SUMPRODUCT((LEFT(Balance!$A$6:$A$75,3)="444")*Balance!I$6:I$75)+SUMPRODUCT((LEFT(Balance!$A$6:$A$75,3)="445")*Balance!I$6:I$75) -> 903100 | H45: =SUMPRODUCT((LEFT(Balance!$A$6:$A$75,3)="443")*Balance!J$6:J$75)+SUMPRODUCT((LEFT(Balance!$A$6:$A$75,3)="444")*Balance!J$6:J$75)+SUMPRODUCT((LEFT(Balance!$A$6:$A$75,3)="445")*Balance!J$6:J$75) -> 1124800 | I45: =SUMPRODUCT((LEFT(Balance!$A$6:$A$75,3)="443")*Balance!K$6:K$75)+SUMPRODUCT((LEFT(Balance!$A$6:$A$75,3)="444")*Balance!K$6:K$75)+SUMPRODUCT((LEFT(Balance!$A$6:$A$75,3)="445")*Balance!K$6:K$75) -> 772000 | J45: =SUMPRODUCT((LEFT(Balance!$A$6:$A$75,3)="443")*Balance!L$6:L$75)+SUMPRODUCT((LEFT(Balance!$A$6:$A$75,3)="444")*Balance!L$6:L$75)+SUMPRODUCT((LEFT(Balance!$A$6:$A$75,3)="445")*Balance!L$6:L$75) -> 965100 | K45: =SUMPRODUCT((LEFT(Balance!$A$6:$A$75,3)="443")*Balance!M$6:M$75)+SUMPRODUCT((LEFT(Balance!$A$6:$A$75,3)="444")*Balance!M$6:M$75)+SUMPRODUCT((LEFT(Balance!$A$6:$A$75,3)="445")*Balance!M$6:M$75) -> 973400 | ... O45: =SUMPRODUCT((LEFT(Balance!$A$6:$A$75,3)="443")*Balance!Q$6:Q$75)+SUMPRODUCT((LEFT(Balance!$A$6:$A$75,3)="444")*Balance!Q$6:Q$75)+SUMPRODUCT((LEFT(Balance!$A$6:$A$75,3)="445")*Balance!Q$6:Q$75) -> 837000 | P45: =O45 -> 837000 | Q45: =IFERROR(INDEX($D45:$O45,MATCH($C$4,$D$9:$O$9,0)),"–") -> 837000
A46: BFR d'exploitation (mensuel) | B46: MAD | D46: =D40+D41-D42+D43-D44-D45 -> 21091300 | E46: =E40+E41-E42+E43-E44-E45 -> 22378700 | F46: =F40+F41-F42+F43-F44-F45 -> 22225000 | G46: =G40+G41-G42+G43-G44-G45 -> 22115900 | H46: =H40+H41-H42+H43-H44-H45 -> 20677200 | I46: =I40+I41-I42+I43-I44-I45 -> 23149000 | J46: =J40+J41-J42+J43-J44-J45 -> 21406900 | K46: =K40+K41-K42+K43-K44-K45 -> 20374600 | ... O46: =O40+O41-O42+O43-O44-O45 -> 21109000 | P46: =O46 -> 21109000 | Q46: =IFERROR(INDEX($D46:$O46,MATCH($C$4,$D$9:$O$9,0)),"–") -> 21109000
A47: DSO — délai de paiement clients | B47: jours | C47: ≈ 60 j | D47: =IFERROR(D41/D11*30,0) -> 60.408669 | E47: =IFERROR(E41/E11*30,0) -> 64.704168 | F47: =IFERROR(F41/F11*30,0) -> 61.211155 | G47: =IFERROR(G41/G11*30,0) -> 63.941729 | H47: =IFERROR(H41/H11*30,0) -> 56.250999 | I47: =IFERROR(I41/I11*30,0) -> 63.763455 | J47: =IFERROR(J41/J11*30,0) -> 61.284901 | K47: =IFERROR(K41/K11*30,0) -> 57.808311 | ... O47: =IFERROR(O41/O11*30,0) -> 56.627737 | P47: =IFERROR(O41/P11*360,0) -> 63.492583 | Q47: =IFERROR(INDEX($D47:$O47,MATCH($C$4,$D$9:$O$9,0)),"–") -> 56.627737
A48: DPO — délai de paiement fournisseurs | B48: jours | C48: 60 à 75 j | D48: =IFERROR(D44/(CPC!D16+CPC!D17+CPC!D18)*30,0) -> 63.056635 | E48: =IFERROR(E44/(CPC!E16+CPC!E17+CPC!E18)*30,0) -> 60.22997 | F48: =IFERROR(F44/(CPC!F16+CPC!F17+CPC!F18)*30,0) -> 65.373241 | G48: =IFERROR(G44/(CPC!G16+CPC!G17+CPC!G18)*30,0) -> 66.455793 | H48: =IFERROR(H44/(CPC!H16+CPC!H17+CPC!H18)*30,0) -> 62.713805 | I48: =IFERROR(I44/(CPC!I16+CPC!I17+CPC!I18)*30,0) -> 60.457072 | J48: =IFERROR(J44/(CPC!J16+CPC!J17+CPC!J18)*30,0) -> 70.465779 | K48: =IFERROR(K44/(CPC!K16+CPC!K17+CPC!K18)*30,0) -> 63.971362 | ... O48: =IFERROR(O44/(CPC!O16+CPC!O17+CPC!O18)*30,0) -> 71.300303 | P48: =IFERROR(O44/(CPC!P16+CPC!P17+CPC!P18)*360,0) -> 78.52349 | Q48: =IFERROR(INDEX($D48:$O48,MATCH($C$4,$D$9:$O$9,0)),"–") -> 71.300303
A49: DIO — stocks en jours de CA | B49: jours | C49: 60 à 90 j | D49: =IFERROR(D40/D11*30,0) -> 76.123839 | E49: =IFERROR(E40/E11*30,0) -> 72.6348 | F49: =IFERROR(F40/F11*30,0) -> 66.247012 | G49: =IFERROR(G40/G11*30,0) -> 69.043283 | H49: =IFERROR(H40/H11*30,0) -> 67.53797 | I49: =IFERROR(I40/I11*30,0) -> 65.439518 | J49: =IFERROR(J40/J11*30,0) -> 69.657089 | K49: =IFERROR(K40/K11*30,0) -> 86.204759 | ... O49: =IFERROR(O40/O11*30,0) -> 63.368613 | P49: =IFERROR(O40/P11*360,0) -> 71.050639 | Q49: =IFERROR(INDEX($D49:$O49,MATCH($C$4,$D$9:$O$9,0)),"–") -> 63.368613
A50: CCC — cycle de conversion du cash (DSO + DIO − DPO) | B50: jours | C50: le plus bas possible | D50: =D47+D49-D48 -> 73.475873 | E50: =E47+E49-E48 -> 77.108998 | F50: =F47+F49-F48 -> 62.084926 | G50: =G47+G49-G48 -> 66.529219 | H50: =H47+H49-H48 -> 61.075164 | I50: =I47+I49-I48 -> 68.745901 | J50: =J47+J49-J48 -> 60.47621 | K50: =K47+K49-K48 -> 80.041708 | ... P50: =P47+P49-P48 -> 56.019733 | Q50: =IFERROR(INDEX($D50:$O50,MATCH($C$4,$D$9:$O$9,0)),"–") -> 48.696047
A52: Code couleur de l'élasticité :
A53: ▲ Levier fort / ▼ REX résiste / ▼ REX progresse | C53: Détail des règles : onglet « Lecture ».
A54: Proportionnel (le REX suit le CA)
A55: ▲ Marge érodée
A56: ▲ Sens contraire / ▼ REX chute plus vite
A57: n.s. = non significatif (CA quasi stable ou REX précédent ≤ 0)

Sheet DASHBOARD
A1: DASHBOARD — AéroTech Maroc — Performance 2023 | T1: ⌂ Accueil
A2: Tableau de bord interactif · Choisissez le mois en D4 : les cartes et la barre dorée se mettent à jour · Données fictives
B4: Mois analysé : | D4: Décembre | F4: ◄ sélecteur de mois
B6: CHIFFRE D'AFFAIRES (MAD) | G6: DSO — DÉLAI CLIENTS | L6: DPO — DÉLAI FOURNISSEURS | Q6: CROISSANCE RÉSULTAT NET
B7: =IFERROR(VLOOKUP($D$4,$B$53:$M$64,2,FALSE()),"–") -> 8220000 | G7: =IFERROR(VLOOKUP($D$4,$B$53:$M$64,6,FALSE()),"–") -> 56.627737 | L7: =IFERROR(VLOOKUP($D$4,$B$53:$M$64,7,FALSE()),"–") -> 71.300303 | Q7: =IFERROR(VLOOKUP($D$4,$B$53:$M$64,8,FALSE()),"–") -> 0.094496105
B9: Marge d'expl. | D9: =IFERROR(VLOOKUP($D$4,$B$53:$M$64,9,FALSE()),"–") -> 0.138382 | G9: Repère | I9: ≈ 60 j | L9: Cycle cash | N9: =IFERROR(VLOOKUP($D$4,$B$53:$M$64,10,FALSE()),"–") -> 48.696047 | Q9: RN du mois | S9: =IFERROR(VLOOKUP($D$4,$B$53:$M$64,3,FALSE()),"–") -> 871000
B47: Astuce : les cartes, la barre dorée du graphique CA et la colonne « Mois sélectionné » du Reporting se pilotent par un sélecteur de mois (D4 ici, C4 dans le Reporting).
B51: Données des graphiques et des cartes (liées automatiquement à l'onglet Reporting — ne pas saisir)
B52: Mois | C52: CA | D52: Résultat net | E52: Valeur ajoutée | F52: REX | G52: DSO | H52: DPO | I52: Croissance RN | J52: Marge expl. | K52: CCC | L52: CA autres mois | M52: CA mois choisi
B53: Janvier | C53: =Reporting!D11 -> 6460000 | D53: =Reporting!D21 -> 374800 | E53: =Reporting!D30 -> 2759000 | F53: =Reporting!D13 -> 547500 | G53: =Reporting!D47 -> 60.408669 | H53: =Reporting!D48 -> 63.056635 | I53: =Reporting!D23 -> 0.085118703 | J53: =Reporting!D15 -> 0.084752322 | K53: =Reporting!D50 -> 73.475873 | L53: =IF(B53=$D$4,0,C53) -> 6460000 | M53: =IF(B53=$D$4,C53,0) -> 0
B54: Février | C54: =Reporting!E11 -> 6862000 | D54: =Reporting!E21 -> 738200 | E54: =Reporting!E30 -> 3165000 | F54: =Reporting!E13 -> 946500 | G54: =Reporting!E47 -> 64.704168 | H54: =Reporting!E48 -> 60.22997 | I54: =Reporting!E23 -> 0.071252358 | J54: =Reporting!E15 -> 0.13793355 | K54: =Reporting!E50 -> 77.108998 | L54: =IF(B54=$D$4,0,C54) -> 6862000 | M54: =IF(B54=$D$4,C54,0) -> 0
B55: Mars | C55: =Reporting!F11 -> 7530000 | D55: =Reporting!F21 -> 794500 | E55: =Reporting!F30 -> 3278000 | F55: =Reporting!F13 -> 1051500 | G55: =Reporting!F47 -> 61.211155 | H55: =Reporting!F48 -> 65.373241 | I55: =Reporting!F23 -> 0.086124402 | J55: =Reporting!F15 -> 0.13964143 | K55: =Reporting!F50 -> 62.084926 | L55: =IF(B55=$D$4,0,C55) -> 7530000 | M55: =IF(B55=$D$4,C55,0) -> 0
B56: Avril | C56: =Reporting!G11 -> 7139000 | D56: =Reporting!G21 -> 628300 | E56: =Reporting!G30 -> 3049000 | F56: =Reporting!G13 -> 815500 | G56: =Reporting!G47 -> 63.941729 | H56: =Reporting!G48 -> 66.455793 | I56: =Reporting!G23 -> 0.084772099 | J56: =Reporting!G15 -> 0.11423169 | K56: =Reporting!G50 -> 66.529219 | L56: =IF(B56=$D$4,0,C56) -> 7139000 | M56: =IF(B56=$D$4,C56,0) -> 0
B57: Mai | C57: =Reporting!H11 -> 7506000 | D57: =Reporting!H21 -> 835000 | E57: =Reporting!H30 -> 3357000 | F57: =Reporting!H13 -> 1101500 | G57: =Reporting!H47 -> 56.250999 | H57: =Reporting!H48 -> 62.713805 | I57: =Reporting!H23 -> 0.054426064 | J57: =Reporting!H15 -> 0.14674927 | K57: =Reporting!H50 -> 61.075164 | L57: =IF(B57=$D$4,0,C57) -> 7506000 | M57: =IF(B57=$D$4,C57,0) -> 0
B58: Juin | C58: =Reporting!I11 -> 7804000 | D58: =Reporting!I21 -> 536800 | E58: =Reporting!I30 -> 3082000 | F58: =Reporting!I13 -> 758500 | G58: =Reporting!I47 -> 63.763455 | H58: =Reporting!I48 -> 60.457072 | I58: =Reporting!I23 -> 0.086419753 | J58: =Reporting!I15 -> 0.097193747 | K58: =Reporting!I50 -> 68.745901 | L58: =IF(B58=$D$4,0,C58) -> 7804000 | M58: =IF(B58=$D$4,C58,0) -> 0
B59: Juillet | C59: =Reporting!J11 -> 7378000 | D59: =Reporting!J21 -> 820200 | E59: =Reporting!J30 -> 3302000 | F59: =Reporting!J13 -> 1031500 | G59: =Reporting!J47 -> 61.284901 | H59: =Reporting!J48 -> 70.465779 | I59: =Reporting!J23 -> 0.082629356 | J59: =Reporting!J15 -> 0.13980754 | K59: =Reporting!J50 -> 60.47621 | L59: =IF(B59=$D$4,0,C59) -> 7378000 | M59: =IF(B59=$D$4,C59,0) -> 0
B60: Août | C60: =Reporting!K11 -> 5968000 | D60: =Reporting!K21 -> 213300 | E60: =Reporting!K30 -> 2609000 | F60: =Reporting!K13 -> 330500 | G60: =Reporting!K47 -> 57.808311 | H60: =Reporting!K48 -> 63.971362 | I60: =Reporting!K23 -> 0.092165899 | J60: =Reporting!K15 -> 0.055378686 | K60: =Reporting!K50 -> 80.041708 | L60: =IF(B60=$D$4,0,C60) -> 5968000 | M60: =IF(B60=$D$4,C60,0) -> 0
B61: Septembre | C61: =Reporting!L11 -> 7347000 | D61: =Reporting!L21 -> 680700 | E61: =Reporting!L30 -> 3157000 | F61: =Reporting!L13 -> 871500 | G61: =Reporting!L47 -> 63.740302 | H61: =Reporting!L48 -> 67.353884 | I61: =Reporting!L23 -> 0.088597473 | J61: =Reporting!L15 -> 0.11861984 | K61: =Reporting!L50 -> 65.210428 | L61: =IF(B61=$D$4,0,C61) -> 7347000 | M61: =IF(B61=$D$4,C61,0) -> 0
B62: Octobre | C62: =Reporting!M11 -> 7894000 | D62: =Reporting!M21 -> 1067400 | E62: =Reporting!M30 -> 3681000 | F62: =Reporting!M13 -> 1387500 | G62: =Reporting!M47 -> 57.742589 | H62: =Reporting!M48 -> 63.695699 | I62: =Reporting!M23 -> 0.05589079 | J62: =Reporting!M15 -> 0.1757664 | K62: =Reporting!M50 -> 58.785932 | L62: =IF(B62=$D$4,0,C62) -> 7894000 | M62: =IF(B62=$D$4,C62,0) -> 0
B63: Novembre | C63: =Reporting!N11 -> 7867000 | D63: =Reporting!N21 -> 850000 | E63: =Reporting!N30 -> 3405000 | F63: =Reporting!N13 -> 1112500 | G63: =Reporting!N47 -> 63.615101 | H63: =Reporting!N48 -> 66.786455 | I63: =Reporting!N23 -> 0.053414302 | J63: =Reporting!N15 -> 0.1414135 | K63: =Reporting!N50 -> 62.049188 | L63: =IF(B63=$D$4,0,C63) -> 7867000 | M63: =IF(B63=$D$4,C63,0) -> 0
B64: Décembre | C64: =Reporting!O11 -> 8220000 | D64: =Reporting!O21 -> 871000 | E64: =Reporting!O30 -> 3662000 | F64: =Reporting!O13 -> 1137500 | G64: =Reporting!O47 -> 56.627737 | H64: =Reporting!O48 -> 71.300303 | I64: =Reporting!O23 -> 0.094496105 | J64: =Reporting!O15 -> 0.138382 | K64: =Reporting!O50 -> 48.696047 | L64: =IF(B64=$D$4,0,C64) -> 0 | M64: =IF(B64=$D$4,C64,0) -> 8220000

Sheet Lecture
A1: LECTURE — Comprendre les indicateurs en 1 minute | F1: ⌂ Accueil
A2: Explications simples, sans jargon, pour tous les lecteurs du reporting
B4: Indicateur | C4: Ce que ça mesure | D4: Comment le lire | E4: Repère / alerte
B5: L'ÉLASTICITÉ CA / REX
B6: Élasticité REX / CA | C6: De combien bouge le résultat d'exploitation quand le chiffre d'affaires bouge de 1 %. | D6: Exemple : CA +10 % et REX +25 % → élasticité 2,5. Chaque point de CA gagné rapporte 2,5 points de REX. | E6: > 1,2 levier fort · 0,8 à 1,2 proportionnel · 0 à 0,8 marge érodée · ≤ 0 sens contraire
B7: Quand le CA baisse | C7: La lecture s'inverse : on regarde si le REX résiste. | D7: Élasticité > 1,2 : le REX chute plus vite que le CA (alerte). Entre 0 et 0,8 : le REX résiste. ≤ 0 : le REX progresse malgré la baisse. | E7: ▼ REX chute plus vite = rouge
B8: n.s. (non significatif) | C8: Le calcul n'est pas affiché car il serait trompeur. | D8: Cas 1 : le CA a bougé de moins de 2 % → on divise par un tout petit chiffre et le résultat explose. Cas 2 : le REX du mois précédent est négatif ou nul → le signe s'inverse ou division par zéro. | E8: Regarder directement les lignes « Variation du CA » et « Variation du REX »
B9: RENTABILITÉ
B10: Marge d'exploitation | C10: Sur 100 MAD de ventes, combien il reste après les coûts d'exploitation. | D10: Plus elle est haute, plus le métier est rentable. Comparer mois par mois et à l'année. | E10: Repère PME aéronautique : 10 % à 15 %
B11: Masse salariale / CA | C11: Le poids des salaires et charges sociales dans les ventes. | D11: S'il monte alors que le CA monte aussi, l'entreprise subit le volume (heures sup., rebuts). | E11: < 30 %
B12: CAF / CA | C12: La part des ventes qui se transforme en argent disponible pour investir ou rembourser. | D12: C'est le résultat « cash » : on rajoute les amortissements qui ne sortent pas de la trésorerie. | E12: > 10 %
B13: Croissance du résultat net | C13: L'évolution du bénéfice par rapport au même mois de l'année précédente. | D13: Comparer au même mois de N-1 évite l'effet des saisons (août, décembre). | E13: Repère : +5 % à +10 %
B14: Densité des charges externes | C14: Le poids des loyers, entretien, honoraires, transports… dans les ventes. | D14: Une hausse sans hausse du CA signale des frais de structure qui dérivent. | E14: < 10 %
B15: Effet de levier opérationnel | C15: La sensibilité « théorique » du REX au CA, calculée avec les charges fixes. | D15: 3x signifie : +1 % de CA ≈ +3 % de REX. Plus il est élevé, plus l'entreprise est exposée en cas de baisse. | E15: 2x à 4x normal · très élevé = forte dépendance aux volumes
B16: SPÉCIFIQUE AÉRONAUTIQUE
B17: Taux de valeur ajoutée locale | C17: La richesse réellement créée dans l'usine par rapport à la production. | D17: Bas : l'entreprise revend surtout de la matière. Très haut avec peu d'achats : matière fournie par le client. | E17: > 40 %
B18: Poids du personnel dans la VA | C18: La part de la richesse créée qui sert à payer le personnel. | D18: Il doit baisser quand la cadence monte (effet d'apprentissage). | E18: < 65 % sain · 65-80 % tendu · > 80 % alerte
B19: REX corrigé du change | C19: Le résultat d'exploitation en réintégrant les gains et pertes de change. | D19: En CGNC, le change sur les ventes en EUR/USD va en résultat financier : on le réintègre pour voir la vraie performance. | E19: Part du change < 20 % du REX
B20: FINANCEMENT ET TRÉSORERIE
B21: Coût moyen de la dette | C21: Le taux d'intérêt réel payé sur les emprunts. | D21: À comparer à la rentabilité de l'exploitation : la dette doit coûter moins qu'elle ne rapporte. | E21: 4 % à 7 %
B22: BFR d'exploitation | C22: L'argent bloqué dans les stocks et les factures clients, moins ce qu'on doit aux fournisseurs. | D22: Plus il grossit, plus il faut de trésorerie pour faire tourner l'usine. | E22: À suivre chaque mois
B23: DSO | C23: Le nombre de jours que mettent les clients à payer. | D23: Plus il est court, mieux c'est. | E23: ≈ 60 jours
B24: DPO | C24: Le nombre de jours que l'entreprise met à payer ses fournisseurs. | D24: Un DPO plus long que le DSO soulage la trésorerie (dans le respect des délais légaux). | E24: 60 à 75 jours
B25: DIO | C25: Le nombre de jours de ventes immobilisés en stock. | D25: Élevé dans l'aéronautique (cycles longs). | E25: 60 à 90 jours
B26: CCC (cycle de cash) | C26: Le nombre de jours entre le paiement des fournisseurs et l'encaissement des clients. | D26: CCC = DSO + DIO − DPO. Plus il est court, moins l'entreprise a besoin de financement. | E26: Le plus bas possible
B28: Code couleur du Reporting
B29: ▲ Levier fort / ▼ REX résiste / ▼ REX progresse
B30: Proportionnel (le REX suit le CA)
B31: ▲ Marge érodée
B32: ▲ Sens contraire / ▼ REX chute plus vite
B33: n.s. = non significatif (CA quasi stable ou REX précédent ≤ 0)
